Workbook

Sheet Summary
A1: SEO Audit: crewhu.com
A3: Audit date | B3: 2026-10-01
A4: Site | B4: https://www.crewhu.com/
A5: Overall health | B5: Needs Work
A6: Method | B6: Based on search-engine index data, competitor SERPs and third-party listings. Direct access to crewhu.com was blocked, so HTML-level items are marked 'verify' (see External Checks).
A8: Findings by priority
A9: Priority | B9: Total | C9: Done | D9: Open | E9: % Done
A10: Critical | B10: =COUNTIF('Action Tracker'!$C$5:$C$21,A10) | C10: =COUNTIFS('Action Tracker'!$C$5:$C$21,A10,'Action Tracker'!$L$5:$L$21,"Done") | D10: =B10-C10 | E10: =IF(B10=0,0,C10/B10)
A11: Important | B11: =COUNTIF('Action Tracker'!$C$5:$C$21,A11) | C11: =COUNTIFS('Action Tracker'!$C$5:$C$21,A11,'Action Tracker'!$L$5:$L$21,"Done") | D11: =B11-C11 | E11: =IF(B11=0,0,C11/B11)
A12: Nice-to-have | B12: =COUNTIF('Action Tracker'!$C$5:$C$21,A12) | C12: =COUNTIFS('Action Tracker'!$C$5:$C$21,A12,'Action Tracker'!$L$5:$L$21,"Done") | D12: =B12-C12 | E12: =IF(B12=0,0,C12/B12)
A13: Total | B13: =SUM(B10:B12) | C13: =SUM(C10:C12) | D13: =SUM(D10:D12) | E13: =IF(B13=0,0,C13/B13)
A15: Top critical issues
A16: C-01 | B16: Duplicate free-trial / demo landing pages indexed
A17: C-02 | B17: Generic one-word titles on core commercial pages
A18: C-03 | B18: Competitors own 'Crewhu alternative' and comparison SERPs
A19: C-04 | B19: No ranking page for '<PSA> CSAT survey' queries
A20: C-05 | B20: Integration docs live on get-help-tnt.crewhu.com subdomain
A22: What's working
B23: Homepage title is strong: brand + both categories + audience.
B24: /blog/how-to-get-more-google-reviews ranks #1 for 'how to get more Google reviews for MSP'.
B25: /blog/employee-recognition-software ranks for 'employee recognition software for MSPs'.
B26: Strong proof points: GO2 Tech (600% more Google reviews), Kraft (45% YoY growth), ACE IT (99% CSAT), 4.7★ on G2 (94 reviews).
A28: Tabs
A29: Action Tracker | B29: All findings with priority, recommendation, owner and status
A30: Quick Wins | B30: Top 5 actions to do first
A31: Title & Meta Rewrites | B31: Copy-paste titles/metas with length checks
A32: Content Plan | B32: New pages to build, with target queries and briefs
A33: Blog Cleanup | B33: Merge / refresh / prune decisions for existing posts
A34: Keyword Clusters | B34: Target clusters; fill in volumes from your SEO tool
A35: External Checks | B35: Items to verify with GSC, Screaming Frog, PSI, Ahrefs
A36: Sources | B36: Evidence URLs

Sheet Action Tracker
A1: Crewhu.com SEO Audit – Action Tracker
A2: Yellow columns (Owner, Due Date, Status, Notes) are for your team to fill in. Status options: Not started / In progress / Done / Won't fix.
A4: ID | B4: Category | C4: Priority | D4: Finding | E4: Affected URLs / Evidence | F4: Why it matters | G4: Recommendation | H4: Effort | I4: Impact | J4: Owner | K4: Due Date | L4: Status | M4: Notes
A5: C-01 | B5: Technical | C5: Critical | D5: Duplicate free-trial / demo landing pages indexed | E5: /start-free-trial, /free-trial-3, /free-trial-g2, /book-a-crewhu-demo-today | F5: Pages compete for the same intent, split link equity, and send organic visitors to G2/paid campaign pages. | G5: Pick one canonical /free-trial and /demo URL. Add noindex,follow (or rel=canonical) to all campaign variants; remove them from the XML sitemap; audit GSC for other -2/-4 variants. | H5: Low | I5: High | J5: SEO lead | L5: Not started | M5: Example row - replace with your owner
A6: C-02 | B6: On-Page | C6: Critical | D6: Generic one-word titles on core commercial pages | E6: /products, /integrations, /about-us, /collect-customer-feedback, /gamify-your-metrics | F6: Highest-intent pages give Google almost no keyword signal and earn low CTR. | G6: Apply the rewrites in the 'Title & Meta Rewrites' tab. | H6: Low | I6: High | L6: Not started
A7: C-03 | B7: Content | C7: Critical | D7: Competitors own 'Crewhu alternative' and comparison SERPs | E7: simplesat.io/alternatives/crewhu-alternative; G2/Capterra/GetApp | F7: Bottom-of-funnel buyers see competitor framing (and outdated pricing) instead of Crewhu's. | G7: Build /compare/crewhu-vs-simplesat, -vs-smileback, -vs-bonusly, -vs-nicereply plus competitor-alternatives pages (see Content Plan). | H7: Medium | I7: High | L7: Not started
A8: C-04 | B8: Content | C8: Critical | D8: No ranking page for '<PSA> CSAT survey' queries | E8: Search: 'ConnectWise CSAT survey integration' | F8: Simplesat, SmileBack and BizRatings rank; Crewhu is absent. Integration info only exists in help docs. | G8: Create /integrations/<psa> landing pages (ConnectWise, Autotask, HaloPSA, Kaseya BMS, Syncro, Zendesk, etc.). | H8: Medium | I8: High | L8: Not started
A9: C-05 | B9: Technical | C9: Critical | D9: Integration docs live on get-help-tnt.crewhu.com subdomain | E9: get-help-tnt.crewhu.com/hc/en-us/... | F9: Subdomain authority largely doesn't benefit www; 'tnt' looks like a test environment. | G9: Short term: link each help article to its marketing integration page. Medium term: move to help.crewhu.com or /help with 301s. | H9: Medium | I9: Medium | L9: Not started
A10: I-01 | B10: On-Page | C10: Important | D10: Non-descriptive URL slugs | E10: /book-a-crewhu-demo-today, /free-trial-3, /gamify-your-metrics, /collect-customer-feedback | F10: Slugs carry little keyword value. | G10: Consider /demo, /free-trial, /gamification, /csat-surveys - only with 301 redirects and only for top pages. | H10: Medium | I10: Low | L10: Not started
A11: I-02 | B11: On-Page | C11: Important | D11: 'Ask Ashley' posts have vague titles | E11: /ask-ashley/ask-ashley-take-one | F11: Titles don't match any search query. | G11: Retitle each post after the question it answers; keep 'Ask Ashley' as an in-body series label. | H11: Low | I11: Medium | L11: Not started
A12: I-03 | B12: Technical | C12: Important | D12: Structured data not confirmed (verify) | E12: Homepage, /pricing, blog | F12: Missing schema forfeits rich results and entity clarity. | G12: Add SoftwareApplication (offers $119/$239/$399, aggregateRating if reviews shown on page), Organization with sameAs, Article/BlogPosting with author, BreadcrumbList, FAQ content. | H12: Low | I12: Medium | L12: Not started
A13: I-04 | B13: Technical | C13: Important | D13: Blog dates inconsistent / stale posts mixed with 2026 content | E13: /blog/* | F13: Mismatched datePublished/dateModified confuses freshness signals. | G13: Align schema dates with visible dates; refresh or merge old posts. | H13: Low | I13: Low | L13: Not started
A14: I-05 | B14: Content | C14: Important | D14: Off-topic / drifting blog posts | E14: /blog/games-for-employee-training, /blog/smart-goal-examples-for-employees, /blog/ebitda-for-msps, /blog/the-daily-huddle-... | F14: Dilutes MSP topical authority. | G14: Refresh with MSP angle if they get traffic; prune or noindex thin pre-2023 posts with no traffic or links. | H14: Medium | I14: Medium | L14: Not started
A15: I-06 | B15: Content | C15: Important | D15: Two overlapping 'employee recognition platforms' guides | E15: /blog/a-guide-to-employee-recognition-platforms-..., /blog/employee-recognition-software | F15: Keyword cannibalization. | G15: 301 the older guide into /blog/employee-recognition-software. | H15: Low | I15: Medium | L15: Not started
A16: I-07 | B16: Content | C16: Important | D16: Only one case study indexed | E16: /case-study/go2-tech | F16: Kraft (45% YoY growth) and ACE IT (99% CSAT) proof isn't searchable. | G16: Build /customers hub; publish each story as its own page with metric-led titles. | H16: Medium | I16: Medium | L16: Not started
A17: I-08 | B17: Content | C17: Important | D17: Weak internal linking from blog to commercial pages | E17: /blog/* | F17: Ranking blog posts don't pass authority or visitors to product pages. | G17: Every post links to ≥1 product/integration/comparison page with descriptive anchor text. | H17: Low | I17: Medium | L17: Not started
... A21: N-03 | B21: On-Page | C21: Nice-to-have | D21: Homepage title could lead with CSAT | E21: / | F21: CSAT/NPS queries carry stronger buying intent. | G21: Optional test: 'Crewhu: CSAT & Employee Recognition Software for MSPs'. | H21: Low | I21: Low | L21: Not started

Sheet Quick Wins
A1: Quick Wins – do these first
A3: # | B3: Action | C3: Tracker ID | D3: Est. effort | E3: Status (from tracker)
A4: 1 | B4: Noindex/canonicalize duplicate trial & demo pages; remove from sitemap | C4: C-01 | D4: ~30 min | E4: =IFERROR(INDEX('Action Tracker'!$L$5:$L$21,MATCH("C-01",'Action Tracker'!$A$5:$A$21,0)),"")
A5: 2 | B5: Rewrite generic titles & meta descriptions (see 'Title & Meta Rewrites') | C5: C-02 | D5: ~1-2 hrs | E5: =IFERROR(INDEX('Action Tracker'!$L$5:$L$21,MATCH("C-02",'Action Tracker'!$A$5:$A$21,0)),"")
A6: 3 | B6: Add SoftwareApplication + Organization schema to homepage and /pricing | C6: I-03 | D6: ~1 hr | E6: =IFERROR(INDEX('Action Tracker'!$L$5:$L$21,MATCH("I-03",'Action Tracker'!$A$5:$A$21,0)),"")
A7: 4 | B7: Publish first comparison page: /compare/crewhu-vs-simplesat | C7: C-03 | D7: ~1-2 days | E7: =IFERROR(INDEX('Action Tracker'!$L$5:$L$21,MATCH("C-03",'Action Tracker'!$A$5:$A$21,0)),"")
A8: 5 | B8: Link help-center integration articles to marketing pages; link Google-reviews blog post to GO2 Tech case study + trial | C8: C-05 / I-08 | D8: ~2 hrs | E8: =IFERROR(INDEX('Action Tracker'!$L$5:$L$21,MATCH("C-05",'Action Tracker'!$A$5:$A$21,0)),"")

Sheet Title & Meta Rewrites
A1: URL | B1: Current title (as indexed) | C1: Proposed title | D1: Proposed meta description | E1: Title length | F1: Meta length
A2: /products | B2: Products | C2: Crewhu Products: CSAT, Recognition & Gamification for MSPs | D2: One platform for MSP client feedback and team engagement: one-click CSAT and NPS surveys, peer recognition, badges, rewards and PSA-powered contests. | E2: =LEN(C2) | F2: =LEN(D2)
A3: /integrations | B3: Integrations | C3: Crewhu Integrations: ConnectWise, Autotask, HaloPSA & More | D3: Connect Crewhu to ConnectWise, Autotask, HaloPSA, Syncro, Zendesk, Teams, Slack and BrightGauge. Surveys sync to tickets; wins reach your team. | E3: =LEN(C3) | F3: =LEN(D3)
A4: /collect-customer-feedback | B4: Collect Customer Feedback | C4: CSAT & NPS Survey Software for MSPs | Crewhu | D4: Send one-click CSAT surveys on every closed ticket and automated NPS surveys, then turn happy clients into Google reviews. Built for MSPs. | E4: =LEN(C4) | F4: =LEN(D4)
A5: /gamify-your-metrics | B5: Gamify Your Metrics | C5: Help Desk Gamification & Technician Leaderboards | Crewhu | D5: Run contests and leaderboards on real PSA KPIs (CSAT, closed tickets, time entries) to motivate MSP technicians. | E5: =LEN(C5) | F5: =LEN(D5)
A6: /about-us | B6: About Us | C6: About Crewhu: Built by an MSP Veteran for MSPs | D6: Founded in 2013 by Stephen Spiegel, Crewhu helps MSPs delight clients and engage their teams with CSAT, recognition and gamification. | E6: =LEN(C6) | F6: =LEN(D6)
A7: /pricing | B7: Pricing & Plans: Employee Recognition Software | C7: Crewhu Pricing & Plans: CSAT + Recognition for MSPs | D7: Compare Crewhu plans: Listen ($119/mo), Recognize ($239/mo) and Grow ($399/mo). Start a free 14-day trial, no credit card required. | E7: =LEN(C7) | F7: =LEN(D7)
A8: /ask-ashley/ask-ashley-take-one | B8: Ask Ashley, Take One | C8: (Retitle after the question the post answers) | D8: (Write after retitling) | E8: =LEN(C8) | F8: =LEN(D8)
A10: Lengths highlighted yellow exceed ~60 chars (title) / ~160 chars (meta) and may be truncated in search results. Current titles are as indexed by search engines and should be confirmed against page source.

Sheet Content Plan
A1: Group | B1: Type | C1: Proposed URL | D1: Target queries | E1: Intent | F1: Priority | G1: Brief / key elements | H1: Owner | I1: Status
A2: A | B2: Comparison | C2: /compare/crewhu-vs-simplesat | D2: crewhu vs simplesat, simplesat alternative | E2: Transactional | F2: Critical | G2: Positioning (feedback-only vs feedback + recognition + gamification), feature table, pricing, best-fit, quotes, FAQ | I2: Not started
A3: A | B3: Comparison | C3: /compare/crewhu-vs-smileback | D3: crewhu vs smileback, smileback alternative | E3: Transactional | F3: Critical | G3: Same template | I3: Not started
A4: A | B4: Comparison | C4: /compare/crewhu-vs-bonusly | D4: bonusly vs crewhu | E4: Transactional | F4: Important | G4: Same template; recognition angle | I4: Not started
A5: A | B5: Comparison | C5: /compare/crewhu-vs-nicereply | D5: nicereply alternative msp | E5: Transactional | F5: Important | G5: Same template | I5: Not started
A6: A | B6: Alternatives | C6: /smileback-alternatives, /simplesat-alternatives | D6: smileback alternatives, simplesat alternatives | E6: Commercial | F6: Important | G6: Fair roundup listing Crewhu first with clear best-fit guidance | I6: Not started
A7: B | B7: Integration | C7: /integrations/connectwise | D7: connectwise csat survey, connectwise nps | E7: Commercial | F7: Critical | G7: What syncs, write-back to notes/custom fields, setup time, screenshot, quote, help-doc link | I7: Not started
A8: B | B8: Integration | C8: /integrations/autotask | D8: autotask csat survey | E8: Commercial | F8: Critical | G8: Same template | I8: Not started
A9: B | B9: Integration | C9: /integrations/halopsa | D9: halopsa csat survey | E9: Commercial | F9: Important | G9: Same template; reference new custom-field write-back | I9: Not started
A10: B | B10: Integration | C10: /integrations/kaseya-bms, /syncro, /zendesk, /freshdesk, /cloudradial | D10: <psa> csat survey | E10: Commercial | F10: Important | G10: Same template | I10: Not started
A11: B | B11: Integration | C11: /integrations/teams, /slack, /brightgauge, /it-glue, /power-bi | D11: <tool> recognition / csat dashboard | E11: Commercial | F11: Nice-to-have | G11: Same template | I11: Not started
A12: C | B12: Solution | C12: /solutions/google-review-generation-for-msps | D12: msp review software, get google reviews msp | E12: Commercial | F12: Important | G12: GO2 Tech 600% proof; compliant (no review gating) positioning | I12: Not started
A13: C | B13: Solution | C13: /solutions/technician-retention | D13: msp technician retention, help desk burnout | E13: Informational | F13: Important | G13: Cite Auvik (60% burned out), Gallup (2.6x job seeking) | I13: Not started
... A20: E | B20: Template | C20: /resources/msp-csat-survey-templates | D20: csat survey template msp | E20: Informational | F20: Nice-to-have | G20: Downloadable/copyable templates | I20: Not started

Sheet Blog Cleanup
A1: URL | B1: Action | C1: Notes | D1: Done?
A2: /blog/a-guide-to-employee-recognition-platforms-and-improving-your-bottom-line | B2: Merge | C2: 301 into /blog/employee-recognition-software (cannibalization)
A3: /blog/games-for-employee-training | B3: Refresh or prune | C3: 2023, off-topic; reframe for MSP technician training or noindex if no traffic
A4: /blog/smart-goal-examples-for-employees | B4: Refresh | C4: Reframe: 'SMART Goal Examples for MSP Technicians'; link to /gamification
A5: /blog/ebitda-for-msps | B5: Keep + link | C5: Relevant to MSP owners; fix date inconsistency; link to retention/CSAT pages
A6: /blog/the-daily-huddle-a-game-changer-for-company-culture | B6: Refresh | C6: Add MSP service-desk angle; link to recognition product
A7: /blog/how-testimonials-reviews-help-sales-marketing | B7: Refresh + link | C7: 2022; link to Google-reviews solution page and GO2 Tech
A8: /blog/how-to-get-more-google-reviews | B8: Protect + link | C8: Ranks #1; add links to GO2 Tech case study and trial
A9: /blog/employee-recognition-software | B9: Protect + link | C9: Ranks for 'employee recognition software for MSPs'; keep updated yearly

Sheet Keyword Clusters
A1: Cluster | B1: Example queries | C1: Intent | D1: Target page | E1: Monthly volume | F1: Keyword difficulty | G1: Current rank
A2: CSAT for MSPs | B2: csat software for msps; msp customer satisfaction survey; csat survey tool connectwise | C2: Commercial | D2: /csat-surveys + /integrations/*
A3: NPS | B3: nps for msps; relational nps survey; good nps score it services | C3: Commercial / Info | D3: /solutions/nps-for-msps; NPS benchmarks post
A4: Recognition | B4: employee recognition software for msps; technician recognition program | C4: Commercial | D4: /employee-recognition + comparison blog post
A5: Gamification | B5: gamification for help desk; technician leaderboard; service desk gamification | C5: Commercial | D5: /gamification
A6: Reviews | B6: how to get google reviews msp; msp review software | C6: Info / Commercial | D6: Reviews blog post + review-generation solution page
A7: Comparisons | B7: crewhu vs smileback; simplesat alternative; smileback alternatives | C7: Transactional | D7: /compare/*
A8: Retention | B8: msp technician retention; help desk burnout | C8: Informational | D8: Retention solution page + blog
A10: Volume, difficulty and rank were not available in this audit – fill from Ahrefs, Semrush or Google Keyword Planner.

Sheet External Checks
A1: Check | B1: Why not verified | C1: Tool | D1: Result / Notes
A2: Raw HTML: meta descriptions, H1s, canonicals, alt text, schema | B2: crewhu.com blocked by audit network policy | C2: Screaming Frog; Google Rich Results Test
A3: robots.txt / XML sitemap contents | B3: Same | C3: Open /robots.txt and /sitemap.xml; GSC > Sitemaps
A4: Index coverage, duplicates, queries | B4: Requires owner access | C4: Google Search Console > Pages, Performance
A5: Core Web Vitals | B5: Requires live render | C5: PageSpeed Insights; CrUX in GSC
A6: Backlink profile & link gap vs simplesat.io / smileback.com | B6: Requires link index | C6: Ahrefs; Semrush
A7: Keyword volumes | B7: Not available | C7: Ahrefs; Semrush; Google Keyword Planner

Sheet Sources
A1: Source | B1: URL
A2: Crewhu homepage | B2: https://www.crewhu.com/
A3: Products | B3: https://www.crewhu.com/products
A4: Integrations | B4: https://www.crewhu.com/integrations
A5: Pricing | B5: https://www.crewhu.com/pricing
A6: Start free trial | B6: https://www.crewhu.com/start-free-trial
A7: Free trial 3 | B7: https://www.crewhu.com/free-trial-3
A8: Free trial G2 | B8: https://www.crewhu.com/free-trial-g2
A9: Book a demo | B9: https://www.crewhu.com/book-a-crewhu-demo-today
A10: GO2 Tech case study | B10: https://www.crewhu.com/case-study/go2-tech
A11: Employee recognition software post | B11: https://www.crewhu.com/blog/employee-recognition-software
A12: Google reviews post | B12: https://www.crewhu.com/blog/how-to-get-more-google-reviews
... A22: LTVplus technician burnout | B22: https://www.ltvplus.com/msp/msp-technician-burnout/
