Workbook

Sheet AIO Keywords
A1: OrbitalX: AI Overview tracking keywords (UK)
A2: 157 candidates. Fill the yellow columns from Semrush (UK database). The sheet ranks them and flags the top 100 to track automatically.
A3: Example of the format (not real data): uk_volume 590 · uk_kd 42 · ai_overview Yes
A5: # | B5: Keyword | C5: Cluster | D5: Intent | E5: Target URL | F5: UK volume | G5: UK KD | H5: AI Overview in SERP? | I5: Score | J5: Rank | K5: Track?
A6: 1 | B6: what is account based marketing | C6: ABM | D6: Informational | E6: /resources/b2b-account-based-marketing | I6: =IF(N(F6)>0,F6*IF(H6="Yes",2,1)*IF(D6="Commercial",1.5,1)+ROW()/1000000,0) -> 0 | J6: =IF(I6>0,COUNTIF($I$6:$I$162,">"&I6)+1,"") | K6: =IF(AND(ISNUMBER(J6),J6<=100),"Track","")
A7: 2 | B7: account based marketing | C7: ABM | D7: Informational | E7: /resources/b2b-account-based-marketing | I7: =IF(N(F7)>0,F7*IF(H7="Yes",2,1)*IF(D7="Commercial",1.5,1)+ROW()/1000000,0) -> 0 | J7: =IF(I7>0,COUNTIF($I$6:$I$162,">"&I7)+1,"") | K7: =IF(AND(ISNUMBER(J7),J7<=100),"Track","")
A8: 3 | B8: abm marketing | C8: ABM | D8: Informational | E8: /resources/b2b-account-based-marketing | I8: =IF(N(F8)>0,F8*IF(H8="Yes",2,1)*IF(D8="Commercial",1.5,1)+ROW()/1000000,0) -> 0 | J8: =IF(I8>0,COUNTIF($I$6:$I$162,">"&I8)+1,"") | K8: =IF(AND(ISNUMBER(J8),J8<=100),"Track","")
A9: 4 | B9: account based marketing strategy | C9: ABM | D9: Informational | E9: /resources/b2b-account-based-marketing | I9: =IF(N(F9)>0,F9*IF(H9="Yes",2,1)*IF(D9="Commercial",1.5,1)+ROW()/1000000,0) -> 0 | J9: =IF(I9>0,COUNTIF($I$6:$I$162,">"&I9)+1,"") | K9: =IF(AND(ISNUMBER(J9),J9<=100),"Track","")
A10: 5 | B10: account based marketing examples | C10: ABM | D10: Informational | E10: /resources/abm-examples (new) | I10: =IF(N(F10)>0,F10*IF(H10="Yes",2,1)*IF(D10="Commercial",1.5,1)+ROW()/1000000,0) -> 0 | J10: =IF(I10>0,COUNTIF($I$6:$I$162,">"&I10)+1,"") | K10: =IF(AND(ISNUMBER(J10),J10<=100),"Track","")
A11: 6 | B11: abm examples | C11: ABM | D11: Informational | E11: /resources/abm-examples (new) | I11: =IF(N(F11)>0,F11*IF(H11="Yes",2,1)*IF(D11="Commercial",1.5,1)+ROW()/1000000,0) -> 0 | J11: =IF(I11>0,COUNTIF($I$6:$I$162,">"&I11)+1,"") | K11: =IF(AND(ISNUMBER(J11),J11<=100),"Track","")
A12: 7 | B12: account based marketing vs inbound marketing | C12: ABM | D12: Informational | E12: /resources/abm-vs-lead-generation | I12: =IF(N(F12)>0,F12*IF(H12="Yes",2,1)*IF(D12="Commercial",1.5,1)+ROW()/1000000,0) -> 0 | J12: =IF(I12>0,COUNTIF($I$6:$I$162,">"&I12)+1,"") | K12: =IF(AND(ISNUMBER(J12),J12<=100),"Track","")
A13: 8 | B13: abm vs demand generation | C13: ABM | D13: Informational | E13: /resources/abm-vs-lead-generation | I13: =IF(N(F13)>0,F13*IF(H13="Yes",2,1)*IF(D13="Commercial",1.5,1)+ROW()/1000000,0) -> 0 | J13: =IF(I13>0,COUNTIF($I$6:$I$162,">"&I13)+1,"") | K13: =IF(AND(ISNUMBER(J13),J13<=100),"Track","")
A14: 9 | B14: abm vs lead generation | C14: ABM | D14: Informational | E14: /resources/abm-vs-lead-generation | I14: =IF(N(F14)>0,F14*IF(H14="Yes",2,1)*IF(D14="Commercial",1.5,1)+ROW()/1000000,0) -> 0 | J14: =IF(I14>0,COUNTIF($I$6:$I$162,">"&I14)+1,"") | K14: =IF(AND(ISNUMBER(J14),J14<=100),"Track","")
A15: 10 | B15: 1:1 abm | C15: ABM | D15: Informational | E15: /services/abm | I15: =IF(N(F15)>0,F15*IF(H15="Yes",2,1)*IF(D15="Commercial",1.5,1)+ROW()/1000000,0) -> 0 | J15: =IF(I15>0,COUNTIF($I$6:$I$162,">"&I15)+1,"") | K15: =IF(AND(ISNUMBER(J15),J15<=100),"Track","")
A16: 11 | B16: one to many abm | C16: ABM | D16: Informational | E16: /services/abm | I16: =IF(N(F16)>0,F16*IF(H16="Yes",2,1)*IF(D16="Commercial",1.5,1)+ROW()/1000000,0) -> 0 | J16: =IF(I16>0,COUNTIF($I$6:$I$162,">"&I16)+1,"") | K16: =IF(AND(ISNUMBER(J16),J16<=100),"Track","")
A17: 12 | B17: 1 to few abm | C17: ABM | D17: Informational | E17: /services/abm | I17: =IF(N(F17)>0,F17*IF(H17="Yes",2,1)*IF(D17="Commercial",1.5,1)+ROW()/1000000,0) -> 0 | J17: =IF(I17>0,COUNTIF($I$6:$I$162,">"&I17)+1,"") | K17: =IF(AND(ISNUMBER(J17),J17<=100),"Track","")
... A162: 157 | B162: employee advocacy | C162: Owned | D162: Informational | E162: /services/owned | I162: =IF(N(F162)>0,F162*IF(H162="Yes",2,1)*IF(D162="Commercial",1.5,1)+ROW()/1000000,0) -> 0 | J162: =IF(I162>0,COUNTIF($I$6:$I$162,">"&I162)+1,"") | K162: =IF(AND(ISNUMBER(J162),J162<=100),"Track","")

Sheet Summary
A1: Summary by cluster
A3: Cluster | B3: Candidates | C3: With UK volume | D3: AIO present | E3: Tracked (top 100) | F3: UK volume tracked
A4: ABM | B4: =COUNTIF('AIO Keywords'!$C$6:$C$162,A4) -> 40 | C4: =COUNTIFS('AIO Keywords'!$C$6:$C$162,A4,'AIO Keywords'!$F$6:$F$162,">0") -> 0 | D4: =COUNTIFS('AIO Keywords'!$C$6:$C$162,A4,'AIO Keywords'!$H$6:$H$162,"Yes") -> 0 | E4: =COUNTIFS('AIO Keywords'!$C$6:$C$162,A4,'AIO Keywords'!$K$6:$K$162,"Track") -> 0 | F4: =SUMIFS('AIO Keywords'!$F$6:$F$162,'AIO Keywords'!$C$6:$C$162,A4,'AIO Keywords'!$K$6:$K$162,"Track") -> 0
A5: Demand gen | B5: =COUNTIF('AIO Keywords'!$C$6:$C$162,A5) -> 20 | C5: =COUNTIFS('AIO Keywords'!$C$6:$C$162,A5,'AIO Keywords'!$F$6:$F$162,">0") -> 0 | D5: =COUNTIFS('AIO Keywords'!$C$6:$C$162,A5,'AIO Keywords'!$H$6:$H$162,"Yes") -> 0 | E5: =COUNTIFS('AIO Keywords'!$C$6:$C$162,A5,'AIO Keywords'!$K$6:$K$162,"Track") -> 0 | F5: =SUMIFS('AIO Keywords'!$F$6:$F$162,'AIO Keywords'!$C$6:$C$162,A5,'AIO Keywords'!$K$6:$K$162,"Track") -> 0
A6: Lead gen | B6: =COUNTIF('AIO Keywords'!$C$6:$C$162,A6) -> 21 | C6: =COUNTIFS('AIO Keywords'!$C$6:$C$162,A6,'AIO Keywords'!$F$6:$F$162,">0") -> 0 | D6: =COUNTIFS('AIO Keywords'!$C$6:$C$162,A6,'AIO Keywords'!$H$6:$H$162,"Yes") -> 0 | E6: =COUNTIFS('AIO Keywords'!$C$6:$C$162,A6,'AIO Keywords'!$K$6:$K$162,"Track") -> 0 | F6: =SUMIFS('AIO Keywords'!$F$6:$F$162,'AIO Keywords'!$C$6:$C$162,A6,'AIO Keywords'!$K$6:$K$162,"Track") -> 0
A7: GTM | B7: =COUNTIF('AIO Keywords'!$C$6:$C$162,A7) -> 20 | C7: =COUNTIFS('AIO Keywords'!$C$6:$C$162,A7,'AIO Keywords'!$F$6:$F$162,">0") -> 0 | D7: =COUNTIFS('AIO Keywords'!$C$6:$C$162,A7,'AIO Keywords'!$H$6:$H$162,"Yes") -> 0 | E7: =COUNTIFS('AIO Keywords'!$C$6:$C$162,A7,'AIO Keywords'!$K$6:$K$162,"Track") -> 0 | F7: =SUMIFS('AIO Keywords'!$F$6:$F$162,'AIO Keywords'!$C$6:$C$162,A7,'AIO Keywords'!$K$6:$K$162,"Track") -> 0
A8: AI | B8: =COUNTIF('AIO Keywords'!$C$6:$C$162,A8) -> 10 | C8: =COUNTIFS('AIO Keywords'!$C$6:$C$162,A8,'AIO Keywords'!$F$6:$F$162,">0") -> 0 | D8: =COUNTIFS('AIO Keywords'!$C$6:$C$162,A8,'AIO Keywords'!$H$6:$H$162,"Yes") -> 0 | E8: =COUNTIFS('AIO Keywords'!$C$6:$C$162,A8,'AIO Keywords'!$K$6:$K$162,"Track") -> 0 | F8: =SUMIFS('AIO Keywords'!$F$6:$F$162,'AIO Keywords'!$C$6:$C$162,A8,'AIO Keywords'!$K$6:$K$162,"Track") -> 0
A9: B2B marketing | B9: =COUNTIF('AIO Keywords'!$C$6:$C$162,A9) -> 32 | C9: =COUNTIFS('AIO Keywords'!$C$6:$C$162,A9,'AIO Keywords'!$F$6:$F$162,">0") -> 0 | D9: =COUNTIFS('AIO Keywords'!$C$6:$C$162,A9,'AIO Keywords'!$H$6:$H$162,"Yes") -> 0 | E9: =COUNTIFS('AIO Keywords'!$C$6:$C$162,A9,'AIO Keywords'!$K$6:$K$162,"Track") -> 0 | F9: =SUMIFS('AIO Keywords'!$F$6:$F$162,'AIO Keywords'!$C$6:$C$162,A9,'AIO Keywords'!$K$6:$K$162,"Track") -> 0
A10: Paid | B10: =COUNTIF('AIO Keywords'!$C$6:$C$162,A10) -> 6 | C10: =COUNTIFS('AIO Keywords'!$C$6:$C$162,A10,'AIO Keywords'!$F$6:$F$162,">0") -> 0 | D10: =COUNTIFS('AIO Keywords'!$C$6:$C$162,A10,'AIO Keywords'!$H$6:$H$162,"Yes") -> 0 | E10: =COUNTIFS('AIO Keywords'!$C$6:$C$162,A10,'AIO Keywords'!$K$6:$K$162,"Track") -> 0 | F10: =SUMIFS('AIO Keywords'!$F$6:$F$162,'AIO Keywords'!$C$6:$C$162,A10,'AIO Keywords'!$K$6:$K$162,"Track") -> 0
A11: PE | B11: =COUNTIF('AIO Keywords'!$C$6:$C$162,A11) -> 3 | C11: =COUNTIFS('AIO Keywords'!$C$6:$C$162,A11,'AIO Keywords'!$F$6:$F$162,">0") -> 0 | D11: =COUNTIFS('AIO Keywords'!$C$6:$C$162,A11,'AIO Keywords'!$H$6:$H$162,"Yes") -> 0 | E11: =COUNTIFS('AIO Keywords'!$C$6:$C$162,A11,'AIO Keywords'!$K$6:$K$162,"Track") -> 0 | F11: =SUMIFS('AIO Keywords'!$F$6:$F$162,'AIO Keywords'!$C$6:$C$162,A11,'AIO Keywords'!$K$6:$K$162,"Track") -> 0
A12: Owned | B12: =COUNTIF('AIO Keywords'!$C$6:$C$162,A12) -> 5 | C12: =COUNTIFS('AIO Keywords'!$C$6:$C$162,A12,'AIO Keywords'!$F$6:$F$162,">0") -> 0 | D12: =COUNTIFS('AIO Keywords'!$C$6:$C$162,A12,'AIO Keywords'!$H$6:$H$162,"Yes") -> 0 | E12: =COUNTIFS('AIO Keywords'!$C$6:$C$162,A12,'AIO Keywords'!$K$6:$K$162,"Track") -> 0 | F12: =SUMIFS('AIO Keywords'!$F$6:$F$162,'AIO Keywords'!$C$6:$C$162,A12,'AIO Keywords'!$K$6:$K$162,"Track") -> 0
A13: Total | B13: =SUM(B4:B12) -> 157 | C13: =SUM(C4:C12) -> 0 | D13: =SUM(D4:D12) -> 0 | E13: =SUM(E4:E12) -> 0 | F13: =SUM(F4:F12) -> 0

Sheet Semrush Paste
A1: Copy each batch into Semrush Keyword Overview (database: UK). 100 keywords max per batch.
A3: Batch 1 | C3: Batch 2
A4: what is account based marketing | C4: flywheel marketing
A5: account based marketing | C5: ai agents for marketing
A6: abm marketing | C6: ai agents for sales
A7: account based marketing strategy | C7: ai sdr
A8: account based marketing examples | C8: ai sdr tools
A9: abm examples | C9: ai in b2b marketing
A10: account based marketing vs inbound marketing | C10: ai marketing strategy
A11: abm vs demand generation | C11: ai marketing automation
A12: abm vs lead generation | C12: ai agent development
A13: 1:1 abm | C13: ai abm
A14: one to many abm | C14: ai account scoring
... A60: google demand gen campaigns | C60: employee advocacy
A61: performance max vs demand gen
A62: dark social
A63: what is dark social
A64: b2b lead generation
A65: lead generation strategies
A66: b2b lead generation strategies
A67: cost per lead
A68: average cost per lead b2b
A69: lead generation outsourcing
A70: lead generation software
A71: ai lead generation
A72: lead generation chatbot
... A103: gtm efficiency

Sheet How to use
A1: How to use this sheet
A3: 1. Semrush Paste tab: copy Batch 1 and Batch 2 into Semrush Keyword Overview, database UK. Export each.
A4: 2. In 'AIO Keywords', fill the yellow columns: UK volume, UK KD, and 'AI Overview in SERP?' (Yes if the SERP Features column lists 'AI overview').
A5: 3. Score, Rank and 'Track?' update automatically. The 100 highest-scoring keywords with UK volume are marked 'Track'.
A6: 4. Filter 'Track?' = Track and load those keywords into your AIO tracking tool (UK, desktop + mobile).
A7: 5. Or connect the Semrush connector in claude.ai and ask Claude to fill the yellow columns for you.
A8: Blue text on yellow = inputs. Black = formulas.
