Workbook

Sheet Dashboard
A1: OrbitalX SEO Audit: Dashboard
A2: orbitalx.com · Audit date 13 Oct 2026 · Sources: full site crawl (152 URLs), Semrush US (12 Oct 2026), Google Search Console (11 Jul – 10 Oct 2026)
A4: Overall health | B4: CRITICAL: brand-only search traffic
A5: Headline: average position improved from ~21 to ~12 in three months, but clicks rose only ~19%. 87% of clicks go to brand pages, the blog converts 0.3% of its impressions into clicks, and the service pages earn almost nothing outside brand sitelinks.
G6: Monthly trend (GSC)
A7: GSC clicks (3 months) | B7: =SUM('GSC Daily'!B5:B96) -> 886 | G7: Month | H7: Clicks | I7: Impressions | J7: Avg position
A8: GSC impressions (3 months) | B8: =SUM('GSC Daily'!C5:C96) -> 31342 | G8: 2026-07 | H8: =SUMIFS('GSC Daily'!B5:B96,'GSC Daily'!F5:F96,G8) -> 163 | I8: =SUMIFS('GSC Daily'!C5:C96,'GSC Daily'!F5:F96,G8) -> 5991 | J8: =SUMPRODUCT(('GSC Daily'!F5:F96=G8)*'GSC Daily'!E5:E96*'GSC Daily'!C5:C96)/I8 -> 21.436939
A9: Average CTR | B9: =B7/B8 -> 0.028268777 | G9: 2026-08 | H9: =SUMIFS('GSC Daily'!B5:B96,'GSC Daily'!F5:F96,G9) -> 312 | I9: =SUMIFS('GSC Daily'!C5:C96,'GSC Daily'!F5:F96,G9) -> 10954 | J9: =SUMPRODUCT(('GSC Daily'!F5:F96=G9)*'GSC Daily'!E5:E96*'GSC Daily'!C5:C96)/I9 -> 19.39245
A10: Avg position: first 30 days | B10: =SUMPRODUCT('GSC Daily'!E5:E34,'GSC Daily'!C5:C34)/SUM('GSC Daily'!C5:C34) -> 20.930568 | G10: 2026-09 | H10: =SUMIFS('GSC Daily'!B5:B96,'GSC Daily'!F5:F96,G10) -> 313 | I10: =SUMIFS('GSC Daily'!C5:C96,'GSC Daily'!F5:F96,G10) -> 11155 | J10: =SUMPRODUCT(('GSC Daily'!F5:F96=G10)*'GSC Daily'!E5:E96*'GSC Daily'!C5:C96)/I10 -> 12.436871
A11: Avg position: last 30 days | B11: =SUMPRODUCT('GSC Daily'!E67:E96,'GSC Daily'!C67:C96)/SUM('GSC Daily'!C67:C96) -> 11.629258 | G11: 2026-10 | H11: =SUMIFS('GSC Daily'!B5:B96,'GSC Daily'!F5:F96,G11) -> 98 | I11: =SUMIFS('GSC Daily'!C5:C96,'GSC Daily'!F5:F96,G11) -> 3242 | J11: =SUMPRODUCT(('GSC Daily'!F5:F96=G11)*'GSC Daily'!E5:E96*'GSC Daily'!C5:C96)/I11 -> 12.002807
A12: Clicks to brand pages (home, team, www, contact) | B12: =SUMIFS('Page Opportunities'!C:C,'Page Opportunities'!B:B,"Brand / sitelink") -> 779 | G12: Jul = 21 days (11–31 Jul); Oct = 10 days (1–10 Oct).
A13: Brand share of page clicks | B13: =B12/SUM('Page Opportunities'!C:C) -> 0.86555556
A14: Blog (/resources/) impressions | B14: =SUMIFS('Page Opportunities'!D:D,'Page Opportunities'!A:A,"*/resources/*") -> 25411 | G14: Devices (GSC)
A15: Blog (/resources/) clicks | B15: =SUMIFS('Page Opportunities'!C:C,'Page Opportunities'!A:A,"*/resources/*") -> 77 | G15: Device | H15: Clicks | I15: Impressions | J15: CTR
A16: Blog CTR | B16: =B15/B14 -> 0.0030301838 | G16: Desktop | H16: 698 | I16: 26079 | J16: =IFERROR(H16/I16,0) -> 0.02676483
A17: UK share of clicks | B17: =INDEX('GSC Countries'!B5:B163,MATCH("United Kingdom",'GSC Countries'!A5:A163,0))/SUM('GSC Countries'!B5:B163) -> 0.37697517 | G17: Mobile | H17: 187 | I17: 5161 | J17: =IFERROR(H17/I17,0) -> 0.036233288
A18: US share of impressions | B18: =INDEX('GSC Countries'!C5:C163,MATCH("United States",'GSC Countries'!A5:A163,0))/SUM('GSC Countries'!C5:C163) -> 0.47970774 | G18: Tablet | H18: 1 | I18: 102 | J18: =IFERROR(H18/I18,0) -> 0.0098039216
A19: US CTR | B19: =INDEX('GSC Countries'!D5:D163,MATCH("United States",'GSC Countries'!A5:A163,0)) -> 0.0075823079
A20: Semrush US ranking keywords (unique) | B20: =SUMPRODUCT(1/COUNTIF('Semrush Keywords'!A5:A100,'Semrush Keywords'!A5:A100)) -> 65
A21: Est. clicks/quarter if CTR gaps closed | B21: =SUM('Page Opportunities'!J:J) -> 299 | C21: Gap = estimated extra clicks per quarter if each page reached the benchmark CTR for its current position (see Page Opportunities). | G21: Top countries by clicks (GSC)
G22: Country | H22: Clicks | I22: Impressions | J22: CTR
A23: Health scorecard | G23: ='GSC Countries'!A5 -> United Kingdom | H23: ='GSC Countries'!B5 -> 334 | I23: ='GSC Countries'!C5 -> 3419 | J23: ='GSC Countries'!D5 -> 0.097689383
A24: Area | B24: Rating | C24: Why | G24: ='GSC Countries'!A6 -> Philippines | H24: ='GSC Countries'!B6 -> 142 | I24: ='GSC Countries'!C6 -> 1462 | J24: ='GSC Countries'!D6 -> 0.097127223
A25: Technical foundation | B25: Good | C25: HTTPS, 1-hop www redirect, self-canonicals, all sitemap URLs return 200 | G25: ='GSC Countries'!A7 -> United States | H25: ='GSC Countries'!B7 -> 114 | I25: ='GSC Countries'!C7 -> 15035 | J25: ='GSC Countries'!D7 -> 0.0075823079
A26: Indexation hygiene | B26: Needs work | C26: app. subdomain (Smartlead), www, 404 URLs and microsites still in Google | G26: ='GSC Countries'!A8 -> South Africa | H26: ='GSC Countries'!B8 -> 46 | I26: ='GSC Countries'!C8 -> 162 | J26: ='GSC Countries'!D8 -> 0.28395062
A27: On-page metadata | B27: Critical | C27: 96 pages share one meta description; weak H1s on hub pages | G27: ='GSC Countries'!A9 -> India | H27: ='GSC Countries'!B9 -> 24 | I27: ='GSC Countries'!C9 -> 1235 | J27: ='GSC Countries'!D9 -> 0.019433198
A28: Internal linking | B28: Critical | C28: ~100 articles reachable only via sitemap; 0 guide→service links | G28: ='GSC Countries'!A10 -> Sweden | H28: ='GSC Countries'!B10 -> 22 | I28: ='GSC Countries'!C10 -> 128 | J28: ='GSC Countries'!D10 -> 0.171875
A29: Content & keywords | B29: Needs work | C29: 52 strong guides, but cannibalisation and 0.3% blog CTR | G29: ='GSC Countries'!A11 -> Netherlands | H29: ='GSC Countries'!B11 -> 16 | I29: ='GSC Countries'!C11 -> 984 | J29: ='GSC Countries'!D11 -> 0.016260163
A30: Commercial visibility | B30: Critical | C30: Service pages rank for no non-brand terms | G30: ='GSC Countries'!A12 -> Germany | H30: ='GSC Countries'!B12 -> 14 | I30: ='GSC Countries'!C12 -> 1190 | J30: ='GSC Countries'!D12 -> 0.011764706
A31: Authority & off-site | B31: Critical | C31: Not listed in any 'best ABM / demand gen agency' roundup
A32: Structured data | B32: Needs work | C32: Organization only, with errors; no Article/Breadcrumb/Person

Sheet Gaps
A1: Gaps: every finding, prioritised
A2: Source column shows where the evidence came from: Crawl (13 Oct 2026), Semrush US (12 Oct 2026), GSC (11 Jul – 10 Oct 2026), SERP research.
A4: ID | B4: Area | C4: Priority | D4: Gap | E4: Evidence | F4: Impact | G4: Fix | H4: Source | I4: Effort | J4: Owner | K4: Status
A5: G01 | B5: Commercial | C5: Critical | D5: Service pages rank for no non-brand terms | E5: Semrush: only /services/abm ranks, #80 for 'abx campaign'. GSC: /services/* impressions come at positions 2–3 with 0.2–0.9% CTR, i.e. brand sitelinks. | F5: No pipeline from search | G5: Make service pages unique (rewrite blocks copied from homepage), add commercial sections (pricing, process, FAQs, Service schema), and point internal links from guides. | H5: Semrush + GSC + Crawl | I5: 1–2 wks | K5: Not started
A6: G02 | B6: Content | C6: Critical | D6: The blog gets impressions but almost no clicks | E6: GSC: /resources/* pages = 25,411 impressions, 77 clicks (0.3% CTR). 98 of 158 pages had 0 clicks. | F6: Wasted visibility | G6: Rewrite titles/meta for high-impression pages (see Page Opportunities); add comparison tables, FAQs, dates in titles. | H6: GSC | I6: 1 wk | K6: Not started
A7: G03 | B7: On-page | C7: Critical | D7: 96 pages share one default meta description | E7: 83 articles + all 13 category/type pages use 'OrbitalX builds profitable pipeline…'. | F7: Low CTR, identical snippets | G7: Set SEO Pro to fall back to the excerpt; hand-write the top 52 guides (drafts in Meta Drafts). | H7: Crawl | I7: 1–2 days | K7: Not started
A8: G04 | B8: Crawlability | C8: Critical | D8: ~100 articles are only reachable via the sitemap | E8: /resources?page=2 shows the same 20 posts and canonicalises to /resources. 26 pages have ≤1 internal link. | F8: Weak crawl priority and PageRank | G8: Crawlable pagination with self-canonicals; related-articles module; footer link to /faqs. | H8: Crawl | I8: 0.5 day dev | K8: Not started
A9: G05 | B9: Content | C9: Critical | D9: Cannibalisation on core terms | E9: 'demand gen company' (480/mo) ranks via /blog-categories/demand-generation #25, not the service page. ABM service queries go to the ABM tools post. Homepage H1 'The ABM agency…' competes with /services/abm. | F9: Google can't pick a winner | G9: Retitle blog posts to informational intent; homepage targets brand + broad; link everything to the service page. | H9: Semrush + Crawl | I9: 2 hrs | K9: Not started
A10: G06 | B10: Indexation | C10: Critical | D10: app.orbitalx.com (titled 'Smartlead') is indexed | E10: 200, no noindex; robots.txt allows /. GSC: 487 impressions. Semrush: ranks for 'orbitx' (4,400/mo), 'orbital x'. | F10: Third-party brand in brand SERP | G10: X-Robots-Tag: noindex via Netlify _headers; rename title. | H10: Crawl + GSC + Semrush | I10: 15 min | K10: Not started
A11: G07 | B11: Off-site | C11: Critical | D11: Absent from every 'best ABM / demand gen agency' roundup | E11: None of the 12 roundups found (Blend, Polaris, B2B Marketing, Directive UK, Digital Litmus, OneMetrik, GTM 8020, RevvGrowth, Growth Syndicate, bestabmagencies, PipeRocket, 310 Creative) lists OrbitalX. | F11: Competitors own the shortlist SERPs | G11: Outreach for inclusion with proof (11.7x ROI, named case studies); build G2/Clutch reviews. | H11: SERP research | I11: Ongoing | K11: Not started
A12: G08 | B12: Indexation | C12: High | D12: /services/earned returns 404 but still gets traffic | E12: GSC: 4 clicks, 67 impressions, avg pos 8.6. Live URL returns 404. | F12: Lost rankings and links | G12: Restore the Earned page (FAQ still references it) or 301 to /services. | H12: GSC + Crawl | I12: 30 min | K12: Not started
A13: G09 | B13: Indexation | C13: High | D13: Dead and typo URLs in Google | E13: GSC shows /resources-v2, /resources/demand-net-vs-performance-max, /resources/account-abased-marketing-tools, /blog-categories/brand-storytelling: all 404 now. | F13: Crawl waste, lost signals | G13: 301 each to the correct page (see Redirect Map). | H13: GSC + Crawl | I13: 30 min | K13: Not started
A14: G10 | B14: Indexation | C14: High | D14: Microsites on subdomains are indexed | E14: GSC: domorewithless., episode4/5/6.domorewithless., marketingunderattack-uk/au., fixcoldoutbound.orbitalx.com. TLS handshake failed from the audit environment (verify). | F14: Diluted brand signals; possibly broken pages | G14: If retired: 301 to /resources pages. If live: fix SSL, add canonical/links back to main site. | H14: GSC | I14: Verify | K14: Not started
A15: G11 | B15: Indexation | C15: High | D15: www.orbitalx.com still shows in Google | E15: GSC: 630 impressions, 7 clicks. Semrush: #10 for 'orbital x'. robots.txt sitemap line and 7 internal links use www. | F15: Split brand signals | G15: Fix robots.txt line, internal links, GBP and sameAs URLs. | H15: GSC + Semrush + Crawl | I15: 1 hr | K15: Not started
A16: G12 | B16: Content | C16: High | D16: Exact and near-duplicate pages | E16: 3 exact duplicates (77–100% overlap) + 4 same-topic pairs (flywheel, MPM, CMO, portfolio blueprint). GSC shows both URLs in several pairs getting impressions. | F16: Split rankings | G16: 301 and merge (see Redirect Map). | H16: Crawl + GSC | I16: 2 hrs | K16: Not started
... A30: G26 | B30: AI search | C30: Low | D30: No llms.txt; some AI citations already exist | E30: Semrush: cited in Google AI Overview / SearchGPT for 3 pages. | F30: Missed AI visibility | G30: Add /llms.txt, clear definitions and FAQ blocks on key pages. | H30: Semrush + Crawl | I30: 1 hr | K30: Not started

Sheet Quick Wins
A1: Quick wins: next 2 weeks
A2: Ranked by impact relative to effort. Score = Impact × (6 − Effort), both on a 1–5 scale (formula). Edit the Owner and Status columns.
A4: # | B4: Action | C4: Gap ID | D4: Owner | E4: Impact (1–5) | F4: Effort (1–5) | G4: Score | H4: Expected result | I4: Due | J4: Status
A5: 1 | B5: Rewrite title + meta on the 6 page-1 pages with <1% CTR (demand-gen-vs-pmax, MQL measurement, StackOne, larger market formula, gtm-systems, b2b-go-to-market-strategy) | C5: G02 | D5: Content | E5: 5 | F5: 1 | G5: =E5*(6-F5) -> 25 | H5: Est. +150 clicks/quarter (see Page Opportunities) | J5: Not started
A6: 2 | B6: Fix cannibalisation: retitle homepage, /resources/account-based-marketing-services, /resources/demand-gen-agency; category intro links to /services/demand-generation | C6: G05 | D6: Content | E6: 5 | F6: 1 | G6: =E6*(6-F6) -> 25 | H6: One clear target for 'demand gen company' (480/mo) | J6: Not started
A7: 3 | B7: Noindex app.orbitalx.com and retitle it from 'Smartlead' | C7: G06 | D7: Dev | E7: 4 | F7: 1 | G7: =E7*(6-F7) -> 20 | H7: Removes third-party brand from 'orbital x' SERP | J7: Not started
A8: 4 | B8: Refresh demand-gen-vs-performance-max: comparison table up top, B2B angle, FAQ (3,004 impr, pos 7.8) | C8: G02 | D8: Content | E8: 5 | F8: 2 | G8: =E8*(6-F8) -> 20 | H8: Highest-impression page-1 article | J8: Not started
A9: 5 | B9: Expand how-to-measure-marketing-qualified-leads-effectively (847 words, 1,700 impr, pos 7, 1 click) | C9: G02 | D9: Content | E9: 4 | F9: 2 | G9: =E9*(6-F9) -> 16 | H9: Page-1 page with 0.06% CTR | J9: Not started
A10: 6 | B10: Add 1–3 service links in each long guide, starting with the ones that rank | C10: G14 | D10: Content | E10: 4 | F10: 2 | G10: =E10*(6-F10) -> 16 | H10: Passes authority to money pages | J10: Not started
A11: 7 | B11: Unique meta descriptions for the 83 articles (top 10 drafted) | C11: G03 | D11: Content | E11: 4 | F11: 2 | G11: =E11*(6-F11) -> 16 | H11: CTR across the blog | J11: Not started
A12: 8 | B12: 301 the 404 URLs still in Google (/services/earned, /resources-v2, 2 typo URLs, brand-storytelling) | C12: G08, G09 | D12: Dev | E12: 3 | F12: 1 | G12: =E12*(6-F12) -> 15 | H12: Recovers clicks and link equity | J12: Not started
A13: 9 | B13: 301 the 3 exact duplicates; merge 4 near-duplicates | C13: G12 | D13: Dev | E13: 3 | F13: 1 | G13: =E13*(6-F13) -> 15 | H13: Consolidates split rankings | J13: Not started
A14: 10 | B14: robots.txt sitemap host, www internal links, GBP/sameAs URLs → non-www | C14: G11 | D14: Dev | E14: 3 | F14: 1 | G14: =E14*(6-F14) -> 15 | H14: Gets www out of the index | J14: Not started
A15: 11 | B15: Crawlable /resources pagination | C15: G04 | D15: Dev | E15: 4 | F15: 3 | G15: =E15*(6-F15) -> 12 | H15: ~100 articles discovered and linked | J15: Not started
A16: 12 | B16: Submit OrbitalX to 5 roundup publishers + G2/Clutch review drive | C16: G07 | D16: Marketing | E16: 4 | F16: 3 | G16: =E16*(6-F16) -> 12 | H16: Shortlist visibility and links | J16: Not started
A17: 13 | B17: Article + Breadcrumb + Person schema, fix Organization, author bylines | C17: G16, G17 | D17: Dev | E17: 3 | F17: 3 | G17: =E17*(6-F17) -> 9 | H17: E-E-A-T and AI citations | J17: Not started

Sheet Page Opportunities
A1: Page opportunities (GSC pages, last 3 months)
A2: Target CTR comes from the benchmark table on the right (an assumption: conservative B2B CTR by position; edit it). Potential and Gap are formulas.
A4: URL | B4: Segment | C4: Clicks | D4: Impressions | E4: CTR | F4: Avg pos | G4: Target CTR | H4: Potential clicks | I4: Notes | J4: Click gap | M4: Position from | N4: Target CTR | O4: Bucket
A5: https://orbitalx.com/ | B5: Brand / sitelink | C5: 702 | D5: 4620 | E5: =IFERROR(C5/D5,0) -> 0.15194805 | F5: 6.5 | G5: =INDEX($N$5:$N$9,MATCH(F5,$M$5:$M$9,1)) -> 0.025 | H5: =ROUND(D5*G5,0) -> 116 | J5: =IF(OR(B5="Brand / sitelink",B5="Sitelink / nav page",B5="Subdomain / www",B5="404: redirect"),0,MAX(0,H5-C5)) -> 0 | M5: 0 | N5: 0.1 | O5: 1–3
A6: https://orbitalx.com/team | B6: Brand / sitelink | C6: 66 | D6: 2813 | E6: =IFERROR(C6/D6,0) -> 0.023462496 | F6: 4.06 | G6: =INDEX($N$5:$N$9,MATCH(F6,$M$5:$M$9,1)) -> 0.05 | H6: =ROUND(D6*G6,0) -> 141 | J6: =IF(OR(B6="Brand / sitelink",B6="Sitelink / nav page",B6="Subdomain / www",B6="404: redirect"),0,MAX(0,H6-C6)) -> 0 | M6: 3.5 | N6: 0.05 | O6: 4–6
A7: https://orbitalx.com/resources/demand-gen-vs-performance-max | B7: Page 1, low CTR | C7: 18 | D7: 3004 | E7: =IFERROR(C7/D7,0) -> 0.0059920107 | F7: 7.78 | G7: =INDEX($N$5:$N$9,MATCH(F7,$M$5:$M$9,1)) -> 0.025 | H7: =ROUND(D7*G7,0) -> 75 | J7: =IF(OR(B7="Brand / sitelink",B7="Sitelink / nav page",B7="Subdomain / www",B7="404: redirect"),0,MAX(0,H7-C7)) -> 57 | M7: 6.5 | N7: 0.025 | O7: 7–10
A8: https://www.orbitalx.com/ | B8: Brand / sitelink | C8: 7 | D8: 630 | E8: =IFERROR(C8/D8,0) -> 0.011111111 | F8: 8.11 | G8: =INDEX($N$5:$N$9,MATCH(F8,$M$5:$M$9,1)) -> 0.025 | H8: =ROUND(D8*G8,0) -> 16 | J8: =IF(OR(B8="Brand / sitelink",B8="Sitelink / nav page",B8="Subdomain / www",B8="404: redirect"),0,MAX(0,H8-C8)) -> 0 | M8: 10.5 | N8: 0.01 | O8: 11–20
A9: https://orbitalx.com/resources/account-based-marketing-webinars | B9: Striking distance (11–20) | C9: 6 | D9: 581 | E9: =IFERROR(C9/D9,0) -> 0.010327022 | F9: 11.09 | G9: =INDEX($N$5:$N$9,MATCH(F9,$M$5:$M$9,1)) -> 0.01 | H9: =ROUND(D9*G9,0) -> 6 | J9: =IF(OR(B9="Brand / sitelink",B9="Sitelink / nav page",B9="Subdomain / www",B9="404: redirect"),0,MAX(0,H9-C9)) -> 0 | M9: 20.5 | N9: 0.003 | O9: 21+
A10: https://orbitalx.com/resource-types/webinars-livestream | B10: OK | C10: 6 | D10: 50 | E10: =IFERROR(C10/D10,0) -> 0.12 | F10: 5.7 | G10: =INDEX($N$5:$N$9,MATCH(F10,$M$5:$M$9,1)) -> 0.05 | H10: =ROUND(D10*G10,0) -> 3 | J10: =IF(OR(B10="Brand / sitelink",B10="Sitelink / nav page",B10="Subdomain / www",B10="404: redirect"),0,MAX(0,H10-C10)) -> 0
A11: https://domorewithless.orbitalx.com/ | B11: Subdomain / www | C11: 5 | D11: 88 | E11: =IFERROR(C11/D11,0) -> 0.056818182 | F11: 5.19 | G11: =INDEX($N$5:$N$9,MATCH(F11,$M$5:$M$9,1)) -> 0.05 | H11: =ROUND(D11*G11,0) -> 4 | J11: =IF(OR(B11="Brand / sitelink",B11="Sitelink / nav page",B11="Subdomain / www",B11="404: redirect"),0,MAX(0,H11-C11)) -> 0
A12: https://orbitalx.com/contact | B12: Brand / sitelink | C12: 4 | D12: 884 | E12: =IFERROR(C12/D12,0) -> 0.0045248869 | F12: 4.9 | G12: =INDEX($N$5:$N$9,MATCH(F12,$M$5:$M$9,1)) -> 0.05 | H12: =ROUND(D12*G12,0) -> 44 | J12: =IF(OR(B12="Brand / sitelink",B12="Sitelink / nav page",B12="Subdomain / www",B12="404: redirect"),0,MAX(0,H12-C12)) -> 0
A13: https://orbitalx.com/resources/inbound-led-outbound | B13: Striking distance (11–20) | C13: 4 | D13: 275 | E13: =IFERROR(C13/D13,0) -> 0.014545455 | F13: 16.49 | G13: =INDEX($N$5:$N$9,MATCH(F13,$M$5:$M$9,1)) -> 0.01 | H13: =ROUND(D13*G13,0) -> 3 | J13: =IF(OR(B13="Brand / sitelink",B13="Sitelink / nav page",B13="Subdomain / www",B13="404: redirect"),0,MAX(0,H13-C13)) -> 0
A14: https://orbitalx.com/services/earned | B14: 404: redirect | C14: 4 | D14: 67 | E14: =IFERROR(C14/D14,0) -> 0.059701493 | F14: 8.64 | G14: =INDEX($N$5:$N$9,MATCH(F14,$M$5:$M$9,1)) -> 0.025 | H14: =ROUND(D14*G14,0) -> 2 | J14: =IF(OR(B14="Brand / sitelink",B14="Sitelink / nav page",B14="Subdomain / www",B14="404: redirect"),0,MAX(0,H14-C14)) -> 0
A15: https://marketingunderattack-uk.orbitalx.com/ | B15: Subdomain / www | C15: 4 | D15: 31 | E15: =IFERROR(C15/D15,0) -> 0.12903226 | F15: 6.9 | G15: =INDEX($N$5:$N$9,MATCH(F15,$M$5:$M$9,1)) -> 0.025 | H15: =ROUND(D15*G15,0) -> 1 | J15: =IF(OR(B15="Brand / sitelink",B15="Sitelink / nav page",B15="Subdomain / www",B15="404: redirect"),0,MAX(0,H15-C15)) -> 0
A16: https://orbitalx.com/resources/account-based-marketing-tools | B16: Deep (21+) | C16: 3 | D16: 6393 | E16: =IFERROR(C16/D16,0) -> 0.00046926326 | F16: 30.16 | G16: =INDEX($N$5:$N$9,MATCH(F16,$M$5:$M$9,1)) -> 0.003 | H16: =ROUND(D16*G16,0) -> 19 | J16: =IF(OR(B16="Brand / sitelink",B16="Sitelink / nav page",B16="Subdomain / www",B16="404: redirect"),0,MAX(0,H16-C16)) -> 16
A17: https://orbitalx.com/services | B17: Sitelink / nav page | C17: 3 | D17: 1541 | E17: =IFERROR(C17/D17,0) -> 0.0019467878 | F17: 3.3 | G17: =INDEX($N$5:$N$9,MATCH(F17,$M$5:$M$9,1)) -> 0.1 | H17: =ROUND(D17*G17,0) -> 154 | J17: =IF(OR(B17="Brand / sitelink",B17="Sitelink / nav page",B17="Subdomain / www",B17="404: redirect"),0,MAX(0,H17-C17)) -> 0
A18: https://orbitalx.com/services/ai-agents | B18: Sitelink / nav page | C18: 3 | D18: 1423 | E18: =IFERROR(C18/D18,0) -> 0.0021082221 | F18: 2.58 | G18: =INDEX($N$5:$N$9,MATCH(F18,$M$5:$M$9,1)) -> 0.1 | H18: =ROUND(D18*G18,0) -> 142 | J18: =IF(OR(B18="Brand / sitelink",B18="Sitelink / nav page",B18="Subdomain / www",B18="404: redirect"),0,MAX(0,H18-C18)) -> 0
A19: https://orbitalx.com/resources/the-larger-market-formula-your-next-b2b-software-success-strategy | B19: Page 1, low CTR | C19: 3 | D19: 715 | E19: =IFERROR(C19/D19,0) -> 0.0041958042 | F19: 7.57 | G19: =INDEX($N$5:$N$9,MATCH(F19,$M$5:$M$9,1)) -> 0.025 | H19: =ROUND(D19*G19,0) -> 18 | J19: =IF(OR(B19="Brand / sitelink",B19="Sitelink / nav page",B19="Subdomain / www",B19="404: redirect"),0,MAX(0,H19-C19)) -> 15
A20: https://orbitalx.com/services/abm | B20: Sitelink / nav page | C20: 3 | D20: 618 | E20: =IFERROR(C20/D20,0) -> 0.0048543689 | F20: 14.87 | G20: =INDEX($N$5:$N$9,MATCH(F20,$M$5:$M$9,1)) -> 0.01 | H20: =ROUND(D20*G20,0) -> 6 | J20: =IF(OR(B20="Brand / sitelink",B20="Sitelink / nav page",B20="Subdomain / www",B20="404: redirect"),0,MAX(0,H20-C20)) -> 0
A21: https://orbitalx.com/resources/demand-gen-funnel | B21: Striking distance (11–20) | C21: 3 | D21: 363 | E21: =IFERROR(C21/D21,0) -> 0.0082644628 | F21: 16.09 | G21: =INDEX($N$5:$N$9,MATCH(F21,$M$5:$M$9,1)) -> 0.01 | H21: =ROUND(D21*G21,0) -> 4 | J21: =IF(OR(B21="Brand / sitelink",B21="Sitelink / nav page",B21="Subdomain / www",B21="404: redirect"),0,MAX(0,H21-C21)) -> 1
... A162: https://orbitalx.com/resources/how-to-prevent-a-pipeline-performance-slump-without-increasing-spend | B162: Page 1, low CTR | C162: 0 | D162: 1 | E162: =IFERROR(C162/D162,0) -> 0 | F162: 10 | G162: =INDEX($N$5:$N$9,MATCH(F162,$M$5:$M$9,1)) -> 0.025 | H162: =ROUND(D162*G162,0) -> 0 | J162: =IF(OR(B162="Brand / sitelink",B162="Sitelink / nav page",B162="Subdomain / www",B162="404: redirect"),0,MAX(0,H162-C162)) -> 0

Sheet Keyword Plan
A1: Keyword plan
A2: Rows marked 'Semrush US' use real data (12 Oct 2026). Rows marked 'New: verify' are target ideas from SERP research: pull UK + US volume/KD in Semrush before committing.
A4: Cluster | B4: Keyword | C4: Data source | D4: US volume | E4: KD | F4: CPC ($) | G4: Current pos (US) | H4: Target URL | I4: Intent | J4: Priority | K4: Action
A5: Demand gen | B5: demand gen vs performance max | C5: Semrush US | D5: 140 | E5: 10 | F5: 34.95 | G5: 20 | H5: /resources/demand-gen-vs-performance-max | I5: Commercial | J5: P1 | K5: Refresh: comparison table, B2B angle, FAQ. GSC: 3,004 impr, pos 7.8, 0.6% CTR.
A6: Demand gen | B6: demand gen software | C6: Semrush US | D6: 140 | E6: 23 | F6: 19.25 | G6: 17 | H6: /resources/demand-gen-software | I6: Commercial | J6: P1 | K6: Ranked tool table + pricing; keyword-first title.
A7: Demand gen | B7: demand gen company | C7: Semrush US | D7: 480 | E7: 43 | F7: 39.51 | G7: 25 | H7: /services/demand-generation | I7: Commercial | J7: P1 | K7: Retarget from category page to service page.
A8: Demand gen | B8: demand generation program | C8: Semrush US | D8: 260 | E8: 34 | F8: 25.16 | G8: 38 | H8: /resources/demand-generation-programs | I8: Informational | J8: P2 | K8: Unique meta, template download, internal links.
A9: Demand gen | B9: demand gen firm | C9: Semrush US | D9: 110 | E9: 38 | F9: 0 | G9: 59 | H9: /services/demand-generation | I9: Commercial | J9: P2 | K9: Synonym coverage on service page (H2/FAQ).
A10: Demand gen | B10: difference between demand gen and lead gen | C10: Semrush US | D10: 50 | E10: 1 | F10: 18.18 | G10: 69 | H10: /resources/lead-generation-vs-demand-generation-understanding-the-differences-and-benefits | I10: Informational | J10: P2 | K10: Merge with what-is-demand-generation into one definitive page.
A11: ABM | B11: account based marketing vendors | C11: Semrush US | D11: 320 | E11: 47 | F11: 29.05 | G11: 76 | H11: /resources/account-based-marketing-tools | I11: Commercial | J11: P2 | K11: ABM vendors/platforms H2s; 2026 comparison table.
A12: ABM | B12: account based marketing platform | C12: Semrush US | D12: 170 | E12: 57 | F12: 91.81 | G12: 73 | H12: /resources/account-based-marketing-tools | I12: Commercial | J12: P2 | K12: Same refresh; CPC $91.81 shows commercial value.
A13: ABM | B13: account based marketing solutions | C13: Semrush US | D13: 210 | E13: 50 | F13: 0 | G13: 79 | H13: /services/abm | I13: Commercial | J13: P2 | K13: Currently ranks via tools post (#79); move intent to service page.
A14: ABM | B14: account based marketing planning services | C14: Semrush US | D14: 170 | E14: 35 | F14: 0 | G14: 69 | H14: /services/abm | I14: Commercial | J14: P1 | K14: Service-intent query ranking via blog (#69); add 'ABM planning' section to service page.
A15: ABM | B15: personalization in account based marketing means | C15: Semrush US | D15: 170 | E15: 21 | F15: 0 | G15: 32 | H15: /resources/account-based-marketing-personalization | I15: Informational | J15: P3 | K15: Add a definition paragraph near the top.
A16: ABM | B16: account based marketing content strategy | C16: Semrush US | D16: 140 | E16: 24 | F16: 0 | G16: 33 | H16: /resources/b2b-account-based-marketing | I16: Informational | J16: P3 | K16: Add content-strategy H2; GSC 1,420 impr at pos 38.
... A18: Paid | B18: performance marketing job category signals | C18: Semrush US | D18: 210 | E18: 9 | F18: 0 | G18: 11 | H18: /resources/performance-marketing-tools | I18: Commercial | J18: P3 | K18: Short section; remove overlap from demand-gen-software.
A19: ABM | B19: abm agency | C19: New: verify | H19: /services/abm | I19: Commercial | J19: P1 | K19: Core money term. SERP = agency pages + 'best ABM agencies' roundups.
A20: ABM | B20: abm agency uk | C20: New: verify | H20: /services/abm | I20: Commercial | J20: P1 | K20: UK is the click-converting market (GSC). Competitors: strategicabm, Gripped, AmbitionABM.
A21: ABM | B21: account based marketing agency | C21: New: verify | H21: /services/abm | I21: Commercial | J21: P1 | K21: Title/H1 variant coverage.
A22: ABM | B22: abm agency pricing / abm cost | C22: New: verify | H22: /pricing (new) | I22: Commercial | J22: P1 | K22: bestabmagencies.com ranks a pricing page; nobody in OrbitalX's tier publishes a clear one.
A23: ABM | B23: abm agency vs in-house | C23: New: verify | H23: /compare/abm-agency-vs-in-house (new) | I23: Commercial | J23: P2 | K23: Reuses homepage 'What it costs to build this yourself' content.
A24: ABM | B24: abm for saas | C24: New: verify | H24: /industries/saas (new) | I24: Commercial | J24: P2 | K24: Most case studies are SaaS.
A25: ABM | B25: abm examples | C25: New: verify | H25: /resources/abm-examples (new) | I25: Informational | J25: P3 | K25: Case-study-led listicle.
A26: Demand gen | B26: b2b demand generation agency uk | C26: New: verify | H26: /services/demand-generation | I26: Commercial | J26: P1 | K26: SERP owned by Blend, Polaris, B2B Marketing, Directive UK roundups.
A27: GTM eng. | B27: gtm engineering | C27: New: verify | H27: /resources/what-is-gtm-engineering (new) | I27: Informational | J27: P1 | K27: SERP is mostly job posts and fractional firms: early-mover opportunity.
A28: GTM eng. | B28: gtm engineering agency / services | C28: New: verify | H28: /services/gtm-engineering | I28: Commercial | J28: P1 | K28: Few established agency pages rank.
A29: GTM eng. | B29: hubspot salesforce lead routing | C29: New: verify | H29: /resources/hubspot-salesforce-lead-routing (new) | I29: Informational | J29: P2 | K29: Supports GTM engineering service.
A30: AI agents | B30: ai sdr / ai agents for b2b marketing | C30: New: verify | H30: /resources/ai-agents-for-b2b-marketing (new) | I30: Informational | J30: P2 | K30: Supports /services/ai-agents.
... A33: Earned | B33: b2b earned media / b2b podcast marketing | C33: New: verify | H33: /services/earned (restore) | I33: Commercial | J33: P3 | K33: Page got clicks before it went 404.

Sheet Content Plan
A1: Content plan: Nov 2026 – Apr 2027
A2: Refresh what already earns impressions first, then build missing commercial pages, then link-worthy assets. ~4 pieces a month.
A4: Month | B4: Type | C4: Working title | D4: Primary keyword | E4: Cluster | F4: URL | G4: Link to | H4: Why / evidence | I4: Owner | J4: Status
A5: Nov 2026 | B5: Refresh | C5: Demand Gen vs Performance Max: Which Google Ads Campaign for B2B? | D5: demand gen vs performance max | E5: Demand gen | F5: /resources/demand-gen-vs-performance-max | G5: /services/paid | H5: GSC 3,004 impr, pos 7.8 | J5: Not started
A6: Nov 2026 | B6: Refresh | C6: How to Measure MQLs (and What to Track Instead) | D6: how to measure marketing qualified leads | E6: Demand gen | F6: /resources/how-to-measure-marketing-qualified-leads-effectively | G6: /services/demand-generation | H6: GSC 1,700 impr, pos 7, 847 words | J6: Not started
A7: Nov 2026 | B7: Service page | C7: Rebuild: B2B Demand Generation Agency | D7: demand gen company / agency | E7: Demand gen | F7: /services/demand-generation | G7: — | H7: Semrush 'demand gen company' #25 via category page | J7: Not started
A8: Nov 2026 | B8: Refresh | C8: 17 Best ABM Tools & Platforms (2026 Comparison) | D8: account based marketing platform / vendors | E8: ABM | F8: /resources/account-based-marketing-tools | G8: /services/abm | H8: GSC 6,393 impr, pos 30 | J8: Not started
A9: Dec 2026 | B9: Service page | C9: Rebuild: Account-Based Marketing Agency (UK) | D9: abm agency uk | E9: ABM | F9: /services/abm | G9: — | H9: Only ranks for 'abx campaign' #80 | J9: Not started
A10: Dec 2026 | B10: Restore | C10: Earned Media for B2B: PR, Podcasts & Communities | D10: b2b earned media | E10: Earned | F10: /services/earned | G10: /services | H10: 404 with 67 impr / 4 clicks | J10: Not started
A11: Dec 2026 | B11: Refresh | C11: Demand Gen Software: 12 Tools Compared | D11: demand gen software | E11: Demand gen | F11: /resources/demand-gen-software | G11: /services/demand-generation | H11: Semrush #17 | J11: Not started
A12: Dec 2026 | B12: Merge | C12: Demand Generation vs Lead Generation: The Definitive Guide | D12: difference between demand gen and lead gen | E12: Demand gen | F12: /resources/lead-generation-vs-demand-generation-… | G12: /services/demand-generation | H12: Merge what-is-demand-generation + 301 | J12: Not started
A13: Jan 2027 | B13: New (commercial) | C13: What Does an ABM Agency Cost? UK Pricing Guide | D13: abm agency pricing | E13: ABM | F13: /pricing | G13: /services/abm, /contact | H13: Competitor bestabmagencies ranks a pricing page | J13: Not started
A14: Jan 2027 | B14: New (commercial) | C14: ABM Agency vs In-House: Cost, Speed and Results | D14: abm agency vs in-house | E14: ABM | F14: /compare/abm-agency-vs-in-house | G14: /services/abm | H14: Reuse homepage cost comparison | J14: Not started
A15: Jan 2027 | B15: New | C15: How to Choose an ABM Agency in the UK (Checklist + Questions) | D15: abm agency uk | E15: ABM | F15: /resources/how-to-choose-an-abm-agency | G15: /services/abm | H15: Captures roundup-style intent fairly | J15: Not started
A16: Jan 2027 | B16: Refresh | C16: StackOne case study: metric-led title and summary | D16: stackone / outbound case study | E16: Proof | F16: /resources/from-data-overload-to-deal-velocity-… | G16: /case-studies | H16: GSC 1,010 impr, pos 8.6, 0 clicks | J16: Not started
A17: Feb 2027 | B17: New (pillar) | C17: What Is GTM Engineering? Definition, Stack and Examples | D17: gtm engineering | E17: GTM eng. | F17: /resources/what-is-gtm-engineering | G17: /services/gtm-engineering | H17: Low-competition SERP | J17: Not started
A18: Feb 2027 | B18: New | C18: HubSpot–Salesforce Lead Routing: A Practical Guide | D18: hubspot salesforce lead routing | E18: GTM eng. | F18: /resources/hubspot-salesforce-lead-routing | G18: /services/gtm-engineering | J18: Not started
A19: Feb 2027 | B19: New | C19: AI Agents for B2B Marketing: 9 Use Cases That Work | D19: ai agents for b2b marketing | E19: AI agents | F19: /resources/ai-agents-for-b2b-marketing | G19: /services/ai-agents | J19: Not started
A20: Feb 2027 | B20: Industry page | C20: ABM & Demand Gen for SaaS Companies | D20: abm for saas | E20: ABM | F20: /industries/saas | G20: /services/abm | H20: Most case studies are SaaS | J20: Not started
A21: Mar 2027 | B21: Industry page | C21: Pipeline Marketing for PE Portfolio Companies | D21: marketing for private equity portfolio companies | E21: PE | F21: /industries/private-equity | G21: /services | H21: Existing PE content + Cylindo | J21: Not started
A22: Mar 2027 | B22: Link asset | C22: State of B2B Pipeline for Lean Teams 2027 (data report) | D22: b2b pipeline benchmarks | E22: Authority | F22: /resources/state-of-b2b-pipeline-2027 | G22: /competitor-intelligence-report | H22: Anonymised 100+ client dataset; pitch to press | J22: Not started
A23: Mar 2027 | B23: Refresh | C23: Account-Based Webinars guide | D23: account based marketing webinars | E23: ABM | F23: /resources/account-based-marketing-webinars | G23: /services/owned | H23: GSC 581 impr, pos 11 | J23: Not started
A24: Mar 2027 | B24: Refresh | C24: B2B Account-Based Marketing: The Full Guide | D24: b2b account based marketing | E24: ABM | F24: /resources/b2b-account-based-marketing | G24: /services/abm | H24: GSC 1,420 impr, pos 38 | J24: Not started
A25: Apr 2027 | B25: New | C25: LinkedIn Ads for B2B: Targeting, Budgets and Benchmarks | D25: linkedin ads b2b | E25: Paid | F25: /resources/linkedin-ads-b2b | G25: /services/paid | H25: /services/paid is thin | J25: Not started
A26: Apr 2027 | B26: Merge | C26: Marketing per Marketer (MPM): The Definitive Metric | D26: marketing per marketer | E26: Authority | F26: /resources/marketing-per-marketer-… | G26: /how-it-works | H26: Merge 2 MPM posts; pitch as benchmark | J26: Not started
A27: Apr 2027 | B27: New | C27: ABM Examples: 10 Campaigns and What They Produced | D27: abm examples | E27: ABM | F27: /resources/abm-examples | G27: /case-studies | H27: Case-study-led | J27: Not started
A28: Apr 2027 | B28: Refresh | C28: Case studies hub: results table + metric-led titles | D28: b2b marketing case studies | E28: Proof | F28: /case-studies | G28: /services/* | H28: 476 words today | J28: Not started

Sheet Competitive Analysis
A1: Competitive analysis
A2: From live search results (13 Oct 2026). Pricing and client names come from third-party roundups and directory profiles, not the competitors' own sites: treat them as indicative.
A4: Competitor | B4: Base | C4: Positioning | D4: Overlap with OrbitalX | E4: SEO / content tactics seen | F4: Pricing signal | G4: Where they beat OrbitalX | H4: What OrbitalX should do
A5: strategicabm | B5: London | C5: ABM-only; strategy, consulting, training and enablement; paid workshops (e.g. ABM Readiness Workshop) | D5: High: direct ABM competitor in the UK | E5: G2 seller profile; listed in salesforge + syncgtm directories; case studies on request by ABM tier | F5: Retainers / consulting-style; six figures a year per program (third-party estimate) | G5: Brand synonymous with 'ABM'; G2 presence; enterprise logos (SAP, Cloudflare per G2) | H5: Match directory/G2 presence; lead with execution + AI (their gap: strategy over execution)
A6: Gripped | B6: London | C6: Content-led B2B SaaS/tech agency: ABM, content, SEO, demand gen, inbound | D6: High: same ICP (UK SaaS) | E6: Ranks its own 'B2B ABM agency' guide; on Polaris UK demand gen list | F6: £3,500–15,000/month (third-party estimate) | G6: SEO-led content that ranks for agency terms; roundup inclusion | H6: Publish an equivalent 'how to choose an ABM agency' guide; get onto the same roundups
A7: Directive | B7: US + /uk/ site | C7: Performance-led: paid, SEO, CRO; ABM inside integrated programs | D7: Medium: demand gen overlap | E7: Runs a UK subfolder with a 'demand generation agencies' roundup; named case studies (Calendly, ZoomInfo, Sumo Logic, Uber Freight) | F7: $10,000–15,000+/month (third-party estimates) | G7: Scale of content, UK localisation, big-logo proof | H7: Out-niche them: 'lean teams' positioning, transparent pricing page, UK-only proof
A8: Powered by Search | B8: Canada/US | C8: Integrated demand gen for B2B SaaS, measured on pipeline | D8: Medium | E8: Self-published 'best demand gen agencies' lists ranking itself first | F8: From $6,000/month (own site, per search summary) | G8: Owns listicle SERPs; publishes pricing | H8: Publish own pricing guide; ask for inclusion in neutral roundups
A9: Blend (blendb2b) | B9: UK/NL | C9: Complex B2B demand gen: brand, website, paid + organic | D9: Medium | E9: Three 2026 'best demand gen agencies' roundups (UK, global, tech), ranking itself first | F9: Not found | G9: Owns 'best demand generation agencies UK' SERP | H9: Pitch for inclusion; build comparison content
A10: Polaris | B10: UK | C10: Organic-led demand gen: SEO, content, digital PR | D10: Medium | E10: Self-ranking UK demand gen list | F10: Not found | G10: Organic + PR link engine | H10: Use the data report + MPM for digital PR
A11: Team Lewis / O8 | B11: Global / US | C11: Full-service agencies with dedicated ABM service pages | D11: Low–Medium | E11: Service pages rank for 'account based marketing services agency' | F11: Not found | G11: Strong domain authority on service pages | H11: Strengthen /services/abm content depth, schema, links
A13: SERP landscape: who ranks for the terms that matter
A14: Keyword | B14: Who ranks (sample) | C14: SERP type | D14: OrbitalX today | E14: How to win
A15: account based marketing services agency | B15: o8.agency, teamlewis.com, 310creative.com (roundup), fahrenheitmarketing.com, fullenrich.com | C15: Agency service pages + roundups | D15: Not in results; /services/abm GSC avg pos 14.9 | E15: Deeper service page (process, tiers, pricing, FAQs, Service schema) + roundup inclusion
A16: best abm agencies (UK) | B16: digitallitmus.com, onemetrik.com, gtm8020.com, revvgrowth.com, thegrowthsyndicate.com, bestabmagencies.com, piperocket.digital | C16: Roundups | D16: Not listed anywhere | E16: Outreach to each publisher with proof pack; Clutch/G2 reviews
A17: abm agency uk | B17: abmatic.ai (blog), gripped.io, salesforge.ai directory, g2.com (strategicabm), syncgtm.com | C17: Blogs + directories | D17: Not in results | E17: Create salesforge/syncgtm/G2 profiles; 'How to choose an ABM agency (UK)' guide
A18: best demand generation agencies uk 2026 | B18: blendb2b.com, b2bmarketing.net, polarisagency.com, directiveconsulting.com/uk | C18: Roundups (mostly self-ranking) | D18: Not listed | E18: Pitch b2bmarketing.net (most independent) and others
A19: demand gen vs performance max | B19: searchatlas.com, blog.adnabu.com, seerinteractive.com, ppc.land | C19: Tool vendors + PPC agencies | D19: GSC avg pos 7.8 (global); Semrush US #20 | E19: Lead with a comparison table and a B2B-specific angle none of them cover
A20: best account based marketing tools 2026 | B20: abmatic.ai, userled.io, nektar.ai, guideflow.com | C20: Vendor roundups (each ranks itself) | D20: GSC avg pos 30; Semrush US #41–85 | E20: Vendor-neutral agency view: pricing, G2 ratings, 'best for' table, '2026' in title
A21: gtm engineering agency | B21: Job posts, agentcommunity.org (GTMpro), SalesPlaybook AG | C21: Jobs + fractional firms | D21: Not ranking | E21: Early-mover: 'What is GTM engineering' pillar + service page

Sheet Outreach Targets
A1: Roundups and directories to get listed in
A2: Found in live SERPs for ABM / demand gen agency terms. OrbitalX was not listed in any roundup.
A4: Site | B4: Type | C4: OrbitalX status | D4: Action | E4: Owner | F4: Status
A5: clutch.co/profile/orbitalx | B5: Directory | C5: Profile exists | D5: Grow reviews; complete services, pricing band and portfolio | F5: Not started
A6: g2.com (Marketing Services) | B6: Directory | C6: Not found | D6: Create seller profile; ask 5 clients for reviews | F6: Not started
A7: salesforge.ai/directory/agencies | B7: Directory | C7: Not found | D7: Submit listing | F7: Not started
A8: syncgtm.com/directory | B8: Directory | C8: Not found | D8: Submit listing | F8: Not started
A9: thegrowthsyndicate.com: top ABM agencies UK | B9: Roundup | C9: Not listed | D9: Pitch with UK case studies | F9: Not started
A10: bestabmagencies.com | B10: Roundup + pricing page | C10: Not listed | D10: Submit for review | F10: Not started
A11: b2bmarketing.net: top UK demand gen agencies | B11: Roundup / benchmark | C11: Not listed | D11: Enter next benchmarking survey | F11: Not started
A12: blendb2b.com: best B2B demand gen agencies (UK) | B12: Roundup | C12: Not listed | D12: Pitch | F12: Not started
A13: polarisagency.com: best demand gen agencies UK | B13: Roundup | C13: Not listed | D13: Pitch | F13: Not started
A14: digitallitmus.com: best ABM agencies | B14: Roundup | C14: Not listed | D14: Pitch | F14: Not started
A15: onemetrik.com: best ABM agencies for SaaS | B15: Roundup | C15: Not listed | D15: Pitch | F15: Not started
A16: gtm8020.com: best ABM agencies for B2B SaaS | B16: Roundup | C16: Not listed | D16: Pitch | F16: Not started
... A19: 310creative.com: top ABM agencies | B19: Roundup | C19: Not listed | D19: Pitch | F19: Not started

Sheet Redirect Map
A1: Redirect map (301)
A2: 404 URLs still showing in GSC, plus duplicate content to consolidate. Implement as 301s, then remove the 'from' URLs from the sitemap.
A4: From | B4: To | C4: Reason | D4: Source | E4: Status
A5: /services/earned | B5: /services (or restore page) | C5: 404, GSC: 4 clicks / 67 impr | D5: GSC | E5: Not started
A6: /resources-v2 | B6: /resources | C6: 404, in GSC | D6: GSC | E6: Not started
A7: /resources/demand-net-vs-performance-max | B7: /resources/demand-gen-vs-performance-max | C7: 404 typo URL in GSC | D7: GSC | E7: Not started
A8: /resources/account-abased-marketing-tools | B8: /resources/account-based-marketing-tools | C8: 404 typo URL in GSC | D8: GSC | E8: Not started
A9: /blog-categories/brand-storytelling | B9: /blog-categories/content-and-brand | C9: 404, in GSC | D9: GSC | E9: Not started
A10: /resources/to-gate-or-un-gate-strategies-on-how-to-make-your-b2b-brand-binge-able-webinar | B10: /resources/to-gate-or-un-gate-strategies-on-how-to-make-your-b2b-brand-binge-able | C10: 100% duplicate | D10: Crawl | E10: Not started
A11: /resources/early-stage-critical-moments-full-episodes | B11: /resources/early-stage-critical-moments-podcast | C11: 87% duplicate | D11: Crawl | E11: Not started
A12: /resources/how-to-prevent-a-pipeline-performance-slump-in-2025-without-increasing-spend | B12: /resources/how-to-prevent-a-pipeline-performance-slump-without-increasing-spend | C12: 77% duplicate; both in GSC | D12: Crawl + GSC | E12: Not started
A13: /resources/the-four-step-flywheel-effect-that-is-defining-gtm-success-in-2025 | B13: /resources/the-4-step-flywheel-effect-a-proven-evergreen-framework-for-gtm-success | C13: Same topic (merge first) | D13: Crawl | E13: Not started
A14: /resources/the-future-b2b-marketing-metric-marketing-per-marketer-mpm | B14: /resources/marketing-per-marketer-how-b2b-will-measure-success-for-the-next-decade | C14: Same topic; both in GSC | D14: Crawl + GSC | E14: Not started
A15: /resources/portfolio-pipeline-blueprint-pe-backed-growth | B15: /resources/the-portfolio-pipeline-marketing-blueprint | C15: Same asset | D15: Crawl | E15: Not started
... A18: Subdomain microsites (domorewithless., marketingunderattack-uk/au., fixcoldoutbound.) | B18: Matching /resources pages (if retired) | C18: Indexed in GSC; SSL handshake failed (verify) | D18: GSC | E18: Not started

Sheet Meta Drafts
A1: Meta description drafts
A2: Under 155 characters. Check each against the article's actual angle before publishing. Length is a formula.
A4: URL | B4: Proposed meta description | C4: Length
A5: / (homepage) | B5: Account-based marketing and demand gen for lean B2B teams. 11.7x average ROI and £300M+ pipeline generated, with a full team and AI system for the cost of one hire. | C5: =LEN(B5) -> 164
A6: /resources/account-based-marketing-tools | B6: Compare 17 account-based marketing tools for intent data, ads, orchestration and analytics, and learn how to build an ABM stack that fits your team. | C6: =LEN(B6) -> 148
A7: /resources/b2b-go-to-market-strategy | B7: Build a B2B go-to-market strategy that turns into pipeline: ICP, positioning, channel mix and the decisions lean teams get wrong. | C7: =LEN(B7) -> 129
A8: /resources/lead-generation-cost-per-lead | B8: B2B cost per lead benchmarks by channel, the CPL formula, and why a "good" CPL depends on pipeline quality, not just price. | C8: =LEN(B8) -> 123
A9: /resources/performance-marketing-tools | B9: The performance marketing tools B2B teams need for attribution, ads, analytics and CRM, and how to build a stack that shows real revenue impact. | C9: =LEN(B9) -> 144
A10: /resources/demand-gen-agency | B10: How to choose a B2B demand generation agency: what to ask, red flags, pricing models and how to measure pipeline impact. | C10: =LEN(B10) -> 120
A11: /resources/b2b-demand-generation-marketing | B11: A complete guide to B2B demand generation: strategy, channels, content and metrics for building predictable pipeline. | C11: =LEN(B11) -> 117
A12: /resources/lead-generation-strategies | B12: B2B lead generation strategies ranked by pipeline impact, from ABM and webinars to outbound and SEO, with what works for lean teams. | C12: =LEN(B12) -> 132
A13: /resources/b2b-marketing-plan | B13: Build a B2B marketing plan that scales pipeline: a step-by-step template for lean teams covering goals, budget, channels and measurement. | C13: =LEN(B13) -> 137
A14: /resources/how-to-measure-account-based-marketing | B14: The ABM metrics that matter: account engagement, pipeline velocity, win rate and ROI. Here's how to measure and report ABM success. | C14: =LEN(B14) -> 131
A15: /resources/gtm-systems | B15: What a GTM system is and how to build one: the data, routing, CRM and feedback loops that connect marketing and sales to revenue. | C15: =LEN(B15) -> 129

Sheet Page Inventory
A1: Page inventory: crawl + Semrush + GSC
A2: One row per sitemap URL (152). GSC columns are blank where the page had no impressions in the last 3 months.
A4: URL | B4: Type | C4: Title | D4: Title len | E4: Meta description | F4: Words | G4: Pages linking here | H4: Semrush kws | I4: Semrush best pos | J4: GSC clicks | K4: GSC impr | L4: GSC avg pos | M4: Issues
A5: https://orbitalx.com | B5: Core | C5: B2B Pipeline Marketing for Lean Teams | OrbitalX | D5: 48 | E5: OrbitalX builds profitable pipeline for lean B2B marketing teams. Turn data into earned marketing programmes that drive revenue — no new hires, no new tools. | F5: 3995 | G5: 152 | H5: 12 | I5: 1 | J5: 702 | K5: 4620 | L5: 6.5
A6: https://orbitalx.com/be-a-guest | B6: Core | C6: Be a Guest on Do More With Less | OrbitalX | D6: 42 | E6: Apply to share your lean-team story on Do More With Less — the B2B podcast for marketers driving outsized pipeline without proportional headcount. | F6: 336 | G6: 152 | H6: 1 | I6: 82 | J6: 1 | K6: 125 | L6: 9.54
A7: https://orbitalx.com/blog-categories/account-based-marketing | B7: Taxonomy | C7: Account Based Marketing | OrbitalX | D7: 34 | E7: OrbitalX builds profitable pipeline for lean B2B marketing teams. An entire team, AI system, and performance for the price of one marketing hire. | F7: 561 | G7: 3 | J7: 0 | K7: 12 | L7: 7.25 | M7: Generic meta
A8: https://orbitalx.com/blog-categories/actionable-strategies | B8: Taxonomy | C8: actionable-strategies | OrbitalX | D8: 32 | E8: OrbitalX builds profitable pipeline for lean B2B marketing teams. An entire team, AI system, and performance for the price of one marketing hire. | F8: 1595 | G8: 1 | J8: 0 | K8: 9 | L8: 15.67 | M8: Generic meta; ≤1 inlink
A9: https://orbitalx.com/blog-categories/b2b-marketing | B9: Taxonomy | C9: B2B Marketing | OrbitalX | D9: 24 | E9: OrbitalX builds profitable pipeline for lean B2B marketing teams. An entire team, AI system, and performance for the price of one marketing hire. | F9: 525 | G9: 2 | J9: 0 | K9: 24 | L9: 5.46 | M9: Generic meta
A10: https://orbitalx.com/blog-categories/case-studies | B10: Taxonomy | C10: Case Studies | OrbitalX | D10: 23 | E10: OrbitalX builds profitable pipeline for lean B2B marketing teams. An entire team, AI system, and performance for the price of one marketing hire. | F10: 483 | G10: 1 | J10: 0 | K10: 13 | L10: 6.08 | M10: Generic meta; ≤1 inlink
A11: https://orbitalx.com/blog-categories/content-and-brand | B11: Taxonomy | C11: Content and Brand | OrbitalX | D11: 28 | E11: OrbitalX builds profitable pipeline for lean B2B marketing teams. An entire team, AI system, and performance for the price of one marketing hire. | F11: 124 | G11: 1 | M11: Generic meta; ≤1 inlink
A12: https://orbitalx.com/blog-categories/demand-generation | B12: Taxonomy | C12: Demand Generation | OrbitalX | D12: 28 | E12: OrbitalX builds profitable pipeline for lean B2B marketing teams. An entire team, AI system, and performance for the price of one marketing hire. | F12: 640 | G12: 2 | H12: 2 | I12: 25 | J12: 0 | K12: 144 | L12: 18.83 | M12: Generic meta
A13: https://orbitalx.com/blog-categories/education | B13: Taxonomy | C13: education | OrbitalX | D13: 20 | E13: OrbitalX builds profitable pipeline for lean B2B marketing teams. An entire team, AI system, and performance for the price of one marketing hire. | F13: 832 | G13: 1 | J13: 0 | K13: 5 | L13: 6 | M13: Generic meta; ≤1 inlink
A14: https://orbitalx.com/blog-categories/gtm-engineering | B14: Taxonomy | C14: GTM Engineering | OrbitalX | D14: 26 | E14: OrbitalX builds profitable pipeline for lean B2B marketing teams. An entire team, AI system, and performance for the price of one marketing hire. | F14: 156 | G14: 2 | J14: 0 | K14: 7 | L14: 2.43 | M14: Generic meta
A15: https://orbitalx.com/blog-categories/pipeline-plays | B15: Taxonomy | C15: Pipeline Plays | OrbitalX | D15: 25 | E15: OrbitalX builds profitable pipeline for lean B2B marketing teams. An entire team, AI system, and performance for the price of one marketing hire. | F15: 173 | G15: 2 | J15: 0 | K15: 5 | L15: 6.6 | M15: Generic meta
A16: https://orbitalx.com/case-studies | B16: Core | C16: Case Studies — B2B Pipeline Results | OrbitalX | D16: 46 | E16: See how lean B2B marketing teams use OrbitalX to build profitable pipeline. Real results from real companies across SaaS, tech, and professional services. | F16: 476 | G16: 152 | J16: 2 | K16: 151 | L16: 11.08
A17: https://orbitalx.com/competitor-intelligence-report | B17: Core | C17: Free Competitor Intelligence Report | OrbitalX | D17: 46 | E17: Discover how your competitors are positioning, which channels they invest in, and where the gaps are. Get a personalised competitor intelligence report within 48 hours. | F17: 523 | G17: 9 | J17: 1 | K17: 55 | L17: 16.07
A18: https://orbitalx.com/contact | B18: Core | C18: Contact Us — Book a Call | OrbitalX | D18: 35 | E18: Get in touch with OrbitalX. Discuss your growth goals, explore partnership opportunities, or book a call to learn how we build pipeline for lean B2B marketing teams. | F18: 230 | G18: 152 | H18: 1 | I18: 13 | J18: 4 | K18: 884 | L18: 4.9
A19: https://orbitalx.com/faqs | B19: Core | C19: FAQs — Frequently Asked Questions | OrbitalX | D19: 44 | E19: Find answers to common questions about OrbitalX services, pricing, onboarding, and how we build profitable pipeline for lean B2B marketing teams. | F19: 1008 | G19: 1 | M19: ≤1 inlink
A20: https://orbitalx.com/how-it-works | B20: Core | C20: How It Works — From ICP Data to Pipeline | OrbitalX | D20: 51 | E20: Our three-step system identifies your ICP buyers, delivers content that shapes their decision criteria, and converts them into pipeline — with performance that compounds monthly. | F20: 1978 | G20: 152 | H20: 1 | I20: 80 | J20: 0 | K20: 258 | L20: 6.36
A21: https://orbitalx.com/legal/privacy-policy | B21: Core | C21: Privacy Policy | OrbitalX | D21: 25 | E21: Read the OrbitalX privacy policy. Learn how we collect, use, and protect your personal data when you use our website and services. | F21: 879 | G21: 152 | H21: 1 | I21: 95 | J21: 1 | K21: 64 | L21: 9.86
A22: https://orbitalx.com/legal/terms-of-service | B22: Core | C22: Terms of Service | OrbitalX | D22: 27 | E22: Review the OrbitalX terms of service. Understand the terms and conditions that govern your use of our website, platform, and marketing services. | F22: 603 | G22: 152 | H22: 1 | I22: 47 | J22: 0 | K22: 124 | L22: 14.52
A23: https://orbitalx.com/platform | B23: Core | C23: Demandwebs Platform — The B2B Pipeline Engine | OrbitalX | D23: 56 | E23: One engine to find, engage, and convert Tier-1 buyers on repeat. Turn data into intelligence, audience, and content with coordinated owned, paid, and earned execution. | F23: 1564 | G23: 152 | H23: 1 | I23: 76 | J23: 2 | K23: 886 | L23: 3.29
A24: https://orbitalx.com/resource-types/blog | B24: Taxonomy | C24: Blog | OrbitalX | D24: 15 | E24: OrbitalX builds profitable pipeline for lean B2B marketing teams. An entire team, AI system, and performance for the price of one marketing hire. | F24: 4352 | G24: 1 | J24: 1 | K24: 10 | L24: 8.8 | M24: Generic meta; ≤1 inlink
A25: https://orbitalx.com/resource-types/download | B25: Taxonomy | C25: Download | OrbitalX | D25: 19 | E25: OrbitalX builds profitable pipeline for lean B2B marketing teams. An entire team, AI system, and performance for the price of one marketing hire. | F25: 311 | G25: 2 | J25: 0 | K25: 147 | L25: 4.07 | M25: Generic meta
A26: https://orbitalx.com/resource-types/video | B26: Taxonomy | C26: Video | OrbitalX | D26: 16 | E26: OrbitalX builds profitable pipeline for lean B2B marketing teams. An entire team, AI system, and performance for the price of one marketing hire. | F26: 458 | G26: 2 | J26: 0 | K26: 19 | L26: 5.84 | M26: Generic meta
A27: https://orbitalx.com/resource-types/webinars-livestream | B27: Taxonomy | C27: Webinars / Livestream | OrbitalX | D27: 32 | E27: OrbitalX builds profitable pipeline for lean B2B marketing teams. An entire team, AI system, and performance for the price of one marketing hire. | F27: 676 | G27: 2 | J27: 6 | K27: 50 | L27: 5.7 | M27: Generic meta
A28: https://orbitalx.com/resources | B28: Core | C28: LearnX — B2B Marketing Resources & Insights | OrbitalX | D28: 54 | E28: Actionable B2B marketing resources, guides, and insights. Learn demand generation strategies, pipeline optimisation techniques, and growth marketing plays. | F28: 1216 | G28: 152 | H28: 2 | I28: 14 | J28: 2 | K28: 1783 | L28: 6.72
A29: https://orbitalx.com/resources/3-actionable-tips-on-how-to-target-your-full-target-market | B29: Article | C29: 3 Actionable Tips on How to Target Your Full Target Market | OrbitalX | D29: 69 | E29: Learn three actionable strategies to reach your full target market. Improve segmentation, messaging, and demand generation performance. | F29: 740 | G29: 3 | J29: 0 | K29: 8 | L29: 19.62
A30: https://orbitalx.com/resources/a-pe-backed-company-cut-marketing-from-12-people-to-3-then-had-its-best-six-months-ever | B30: Article | C30: A PE-Backed Company Cut Marketing From 12 People to 3. Then Had Its Best Six Months Ever. | OrbitalX | D30: 100 | E30: OrbitalX builds profitable pipeline for lean B2B marketing teams. An entire team, AI system, and performance for the price of one marketing hire. | F30: 1649 | G30: 115 | J30: 0 | K30: 34 | L30: 4.29 | M30: Generic meta
A31: https://orbitalx.com/resources/abm-content-that-breaks-through-why-only-undeniably-human-stories-convert-tier-one-accounts | B31: Article | C31: How to build B2B content that drives pipeline in a market drowning in AI-generated noise | OrbitalX | D31: 99 | E31: OrbitalX builds profitable pipeline for lean B2B marketing teams. An entire team, AI system, and performance for the price of one marketing hire. | F31: 383 | G31: 2 | J31: 0 | K31: 6 | L31: 4.5 | M31: Generic meta; Thin
A32: https://orbitalx.com/resources/abm-for-lean-teams-ai-agents-rewriting-abm-account-playbook | B32: Article | C32: ABM for lean teams: How AI agents are rewriting the ABM account playbook | OrbitalX | D32: 83 | E32: OrbitalX builds profitable pipeline for lean B2B marketing teams. An entire team, AI system, and performance for the price of one marketing hire. | F32: 667 | G32: 1 | J32: 0 | K32: 20 | L32: 8.55 | M32: Generic meta; ≤1 inlink
A33: https://orbitalx.com/resources/abm-vs-lead-generation | B33: Article | C33: ABM vs. Lead Generation: Which Strategy Is Right for Your Business? | OrbitalX | D33: 78 | E33: OrbitalX builds profitable pipeline for lean B2B marketing teams. An entire team, AI system, and performance for the price of one marketing hire. | F33: 3607 | G33: 4 | J33: 0 | K33: 52 | L33: 11.9 | M33: Generic meta
A34: https://orbitalx.com/resources/account-based-marketing-analytics | B34: Article | C34: Account-Based Marketing Analytics the RIGHT Way: Proving Your Strategy’s Value | OrbitalX | D34: 89 | E34: OrbitalX builds profitable pipeline for lean B2B marketing teams. An entire team, AI system, and performance for the price of one marketing hire. | F34: 3400 | G34: 10 | J34: 1 | K34: 46 | L34: 6.85 | M34: Generic meta
A35: https://orbitalx.com/resources/account-based-marketing-personalization | B35: Article | C35: A Practical Guide to Account-Based Marketing Personalization at Scale | OrbitalX | D35: 80 | E35: OrbitalX builds profitable pipeline for lean B2B marketing teams. An entire team, AI system, and performance for the price of one marketing hire. | F35: 3727 | G35: 7 | H35: 2 | I35: 32 | J35: 0 | K35: 885 | L35: 19.9 | M35: Generic meta
A36: https://orbitalx.com/resources/account-based-marketing-services | B36: Article | C36: Account-Based Marketing Services: Why B2B Teams Need a Signal-Based System | OrbitalX | D36: 85 | E36: OrbitalX builds profitable pipeline for lean B2B marketing teams. An entire team, AI system, and performance for the price of one marketing hire. | F36: 3055 | G36: 6 | J36: 0 | K36: 35 | L36: 19.2 | M36: Generic meta
A37: https://orbitalx.com/resources/account-based-marketing-software | B37: Article | C37: Account-Based Marketing Software Explained | OrbitalX | D37: 53 | E37: OrbitalX builds profitable pipeline for lean B2B marketing teams. An entire team, AI system, and performance for the price of one marketing hire. | F37: 2903 | G37: 3 | H37: 3 | I37: 31 | J37: 0 | K37: 664 | L37: 25.09 | M37: Generic meta
A38: https://orbitalx.com/resources/account-based-marketing-tactics | B38: Article | C38: Beyond the Basics: Account-Based Marketing Tactics That Actually Bring Results | OrbitalX | D38: 89 | E38: OrbitalX builds profitable pipeline for lean B2B marketing teams. An entire team, AI system, and performance for the price of one marketing hire. | F38: 2726 | G38: 8 | J38: 0 | K38: 34 | L38: 11.65 | M38: Generic meta
A39: https://orbitalx.com/resources/account-based-marketing-tools | B39: Article | C39: 17 Top Account-Based Marketing Tools for a Scalable ABM Strategy | OrbitalX | D39: 75 | E39: OrbitalX builds profitable pipeline for lean B2B marketing teams. An entire team, AI system, and performance for the price of one marketing hire. | F39: 5433 | G39: 5 | H39: 16 | I39: 17 | J39: 3 | K39: 6393 | L39: 30.16 | M39: Generic meta
A40: https://orbitalx.com/resources/account-based-marketing-webinars | B40: Article | C40: How to Master Account-Based Webinars for High-Value Growth | OrbitalX | D40: 69 | E40: OrbitalX builds profitable pipeline for lean B2B marketing teams. An entire team, AI system, and performance for the price of one marketing hire. | F40: 4405 | G40: 7 | J40: 6 | K40: 581 | L40: 11.09 | M40: Generic meta
A41: https://orbitalx.com/resources/ai-lead-generation | B41: Article | C41: AI Lead Generation: What Actually Works in High-Value B2B | OrbitalX | D41: 68 | E41: OrbitalX builds profitable pipeline for lean B2B marketing teams. An entire team, AI system, and performance for the price of one marketing hire. | F41: 4248 | G41: 3 | H41: 1 | I41: 13 | J41: 0 | K41: 81 | L41: 11.07 | M41: Generic meta
A42: https://orbitalx.com/resources/b2b-account-based-marketing | B42: Article | C42: B2B Account-Based Marketing: The Full Guide to Doing It Right | OrbitalX | D42: 72 | E42: OrbitalX builds profitable pipeline for lean B2B marketing teams. An entire team, AI system, and performance for the price of one marketing hire. | F42: 2620 | G42: 16 | H42: 4 | I42: 1 | J42: 2 | K42: 1420 | L42: 38.31 | M42: Generic meta
A43: https://orbitalx.com/resources/b2b-content-marketing-funnel | B43: Article | C43: B2B Content Marketing Funnel: Stages, Strategies, and How to Build One That Converts | OrbitalX | D43: 95 | E43: OrbitalX builds profitable pipeline for lean B2B marketing teams. An entire team, AI system, and performance for the price of one marketing hire. | F43: 3483 | G43: 115 | J43: 0 | K43: 89 | L43: 10.01 | M43: Generic meta
A44: https://orbitalx.com/resources/b2b-demand-gen | B44: Article | C44: The Old B2B Demand Gen Playbook Is Breaking: What Lean B2B Teams Are Doing Instead | OrbitalX | D44: 93 | E44: OrbitalX builds profitable pipeline for lean B2B marketing teams. An entire team, AI system, and performance for the price of one marketing hire. | F44: 3511 | G44: 4 | J44: 1 | K44: 52 | L44: 7.65 | M44: Generic meta
A45: https://orbitalx.com/resources/b2b-demand-generation-marketing | B45: Article | C45: B2B Demand Generation Marketing: A Complete Guide to Building Predictable Pipeline | OrbitalX | D45: 93 | E45: OrbitalX builds profitable pipeline for lean B2B marketing teams. An entire team, AI system, and performance for the price of one marketing hire. | F45: 4415 | G45: 8 | J45: 1 | K45: 70 | L45: 9.06 | M45: Generic meta
A46: https://orbitalx.com/resources/b2b-go-to-market-strategy | B46: Article | C46: B2B Go-To-Market Strategy: The Decisions That Turn Market Plans Into Pipeline | OrbitalX | D46: 88 | E46: OrbitalX builds profitable pipeline for lean B2B marketing teams. An entire team, AI system, and performance for the price of one marketing hire. | F46: 5036 | G46: 3 | H46: 4 | I46: 31 | J46: 1 | K46: 289 | L46: 9.43 | M46: Generic meta
A47: https://orbitalx.com/resources/b2b-market-segmentation | B47: Article | C47: B2B Market Segmentation: Building a Commercial Prioritization System | OrbitalX | D47: 79 | E47: OrbitalX builds profitable pipeline for lean B2B marketing teams. An entire team, AI system, and performance for the price of one marketing hire. | F47: 3619 | G47: 3 | J47: 0 | K47: 61 | L47: 6.46 | M47: Generic meta
A48: https://orbitalx.com/resources/b2b-marketing | B48: Article | C48: B2B Marketing In A Nutshell: Strategy, Buyer Behavior, and Modern Revenue Tactics | OrbitalX | D48: 92 | E48: OrbitalX builds profitable pipeline for lean B2B marketing teams. An entire team, AI system, and performance for the price of one marketing hire. | F48: 5703 | G48: 5 | H48: 1 | I48: 45 | J48: 0 | K48: 243 | L48: 12.43 | M48: Generic meta
A49: https://orbitalx.com/resources/b2b-marketing-and-sales-alignment | B49: Article | C49: Driving B2B Revenue Growth Through Marketing and Sales Alignment in Long Sales Cycles | OrbitalX | D49: 96 | E49: OrbitalX builds profitable pipeline for lean B2B marketing teams. An entire team, AI system, and performance for the price of one marketing hire. | F49: 3706 | G49: 6 | J49: 1 | K49: 113 | L49: 12.73 | M49: Generic meta
A50: https://orbitalx.com/resources/b2b-marketing-automation | B50: Article | C50: B2B Marketing Automation Strategy: How AI and Systems Drive Real Results | OrbitalX | D50: 83 | E50: OrbitalX builds profitable pipeline for lean B2B marketing teams. An entire team, AI system, and performance for the price of one marketing hire. | F50: 3517 | G50: 9 | J50: 0 | K50: 55 | L50: 11 | M50: Generic meta
A51: https://orbitalx.com/resources/b2b-marketing-automation-examples | B51: Article | C51: B2B Marketing Automation Examples That Turn Buyer Signals Into Pipeline | OrbitalX | D51: 82 | E51: OrbitalX builds profitable pipeline for lean B2B marketing teams. An entire team, AI system, and performance for the price of one marketing hire. | F51: 4746 | G51: 4 | J51: 0 | K51: 65 | L51: 10.85 | M51: Generic meta
A52: https://orbitalx.com/resources/b2b-marketing-budget | B52: Article | C52: Why Most B2B Marketing Budgets Waste Pipeline Before Campaigns Even Launch | OrbitalX | D52: 85 | E52: OrbitalX builds profitable pipeline for lean B2B marketing teams. An entire team, AI system, and performance for the price of one marketing hire. | F52: 3391 | G52: 3 | J52: 0 | K52: 209 | L52: 13.23 | M52: Generic meta
A53: https://orbitalx.com/resources/b2b-marketing-consultant | B53: Article | C53: B2B Marketing Consultant: When Pipeline Is the Problem | OrbitalX | D53: 65 | E53: OrbitalX builds profitable pipeline for lean B2B marketing teams. An entire team, AI system, and performance for the price of one marketing hire. | F53: 3647 | G53: 4 | J53: 1 | K53: 32 | L53: 8.66 | M53: Generic meta
A54: https://orbitalx.com/resources/b2b-marketing-funnel | B54: Article | C54: B2B Marketing Funnel Guide: How Modern Funnels Actually Convert Buyers | OrbitalX | D54: 81 | E54: OrbitalX builds profitable pipeline for lean B2B marketing teams. An entire team, AI system, and performance for the price of one marketing hire. | F54: 3576 | G54: 7 | J54: 1 | K54: 128 | L54: 8.35 | M54: Generic meta
A55: https://orbitalx.com/resources/b2b-marketing-ideas | B55: Article | C55: The Best B2B Marketing Ideas for Generating High Quality Pipeline | OrbitalX | D55: 76 | E55: OrbitalX builds profitable pipeline for lean B2B marketing teams. An entire team, AI system, and performance for the price of one marketing hire. | F55: 3202 | G55: 3 | J55: 0 | K55: 55 | L55: 8.13 | M55: Generic meta
A56: https://orbitalx.com/resources/b2b-marketing-metrics | B56: Article | C56: B2B Marketing Metrics That Actually Help You Make Better Decisions | OrbitalX | D56: 77 | E56: OrbitalX builds profitable pipeline for lean B2B marketing teams. An entire team, AI system, and performance for the price of one marketing hire. | F56: 3021 | G56: 3 | J56: 1 | K56: 89 | L56: 7.93 | M56: Generic meta
A57: https://orbitalx.com/resources/b2b-marketing-plan | B57: Article | C57: How Lean B2B Teams Build Marketing Plans That Scale Pipeline | OrbitalX | D57: 71 | E57: OrbitalX builds profitable pipeline for lean B2B marketing teams. An entire team, AI system, and performance for the price of one marketing hire. | F57: 3883 | G57: 3 | J57: 0 | K57: 78 | L57: 10.31 | M57: Generic meta
A58: https://orbitalx.com/resources/b2b-marketing-strategies | B58: Article | C58: Top 2026 B2B Marketing Strategies To Try: AI Personalization, Video Funnels, and More | OrbitalX | D58: 96 | E58: OrbitalX builds profitable pipeline for lean B2B marketing teams. An entire team, AI system, and performance for the price of one marketing hire. | F58: 2569 | G58: 4 | J58: 0 | K58: 80 | L58: 9.7 | M58: Generic meta
A59: https://orbitalx.com/resources/b2b-marketing-trends-2026 | B59: Article | C59: Clicks Don’t Matter Anymore: The 2026 B2B Marketing Trends Playbook | OrbitalX | D59: 78 | E59: OrbitalX builds profitable pipeline for lean B2B marketing teams. An entire team, AI system, and performance for the price of one marketing hire. | F59: 2857 | G59: 11 | J59: 0 | K59: 154 | L59: 8.42 | M59: Generic meta
A60: https://orbitalx.com/resources/b2b-marketing-webinars | B60: Article | C60: How to Create a B2B Marketing Webinar Strategy That Generates Pipeline | OrbitalX | D60: 81 | E60: OrbitalX builds profitable pipeline for lean B2B marketing teams. An entire team, AI system, and performance for the price of one marketing hire. | F60: 2662 | G60: 3 | J60: 1 | K60: 34 | L60: 5.32 | M60: Generic meta
... A62: https://orbitalx.com/resources/b2b-referral-marketing | B62: Article | C62: B2B Referral Marketing: How to Build a Program That Drives Qualified Growth | OrbitalX | D62: 86 | E62: OrbitalX builds profitable pipeline for lean B2B marketing teams. An entire team, AI system, and performance for the price of one marketing hire. | F62: 3611 | G62: 115 | J62: 0 | K62: 38 | L62: 9.05 | M62: Generic meta
A63: https://orbitalx.com/resources/behind-the-numbers-how-yieldify-made-every-rep-count | B63: Article | C63: Behind the Numbers: How Yieldify Made Every Rep Count | OrbitalX | D63: 64 | E63: See how Yieldify maximised sales efficiency and performance. Discover the demand generation approach that helped every rep generate more impact. | F63: 604 | G63: 9 | H63: 1 | I63: 20 | J63: 1 | K63: 674 | L63: 13.32
A64: https://orbitalx.com/resources/big-uncommon-thinking-how-top-c-suite-leaders-use-uncommon-thinking-to-spark-money-making-b2b-growth-machines | B64: Article | C64: Big Uncommon Thinking: How top C-Suite leaders use 'Uncommon Thinking' to spark money-making B2B growth machines | OrbitalX | D64: 123 | E64: OrbitalX builds profitable pipeline for lean B2B marketing teams. An entire team, AI system, and performance for the price of one marketing hire. | F64: 590 | G64: 2 | J64: 0 | K64: 2 | L64: 5.5 | M64: Generic meta; Thin
A65: https://orbitalx.com/resources/building-trust-in-b2b-the-cornerstone-of-long-term-success | B65: Article | C65: Building Trust in B2B: The Cornerstone of Long-Term Success | OrbitalX | D65: 70 | E65: Trust is the foundation of long-term B2B success. Learn how brands build credibility, authority, and lasting customer relationships. | F65: 1136 | G65: 3 | J65: 0 | K65: 11 | L65: 11.09
A66: https://orbitalx.com/resources/building-world-class-watchable-content | B66: Article | C66: Building World-Class Watchable Content | OrbitalX | D66: 49 | E66: Learn how to create world-class watchable content that captures attention. Discover formats that drive engagement and brand authority in B2B. | F66: 956 | G66: 5 | J66: 1 | K66: 68 | L66: 8.47
A67: https://orbitalx.com/resources/critical-moments-season-2 | B67: Article | C67: Critical Moments Season 2 — B2B Video Series | OrbitalX | D67: 55 | E67: Watch Critical Moments Season 2: candid conversations with B2B leaders on the decisions that shaped pipeline, positioning, and GTM execution. | F67: 529 | G67: 1 | J67: 0 | K67: 3 | L67: 4.67 | M67: Thin; ≤1 inlink
A68: https://orbitalx.com/resources/demand-gen-agency | B68: Article | C68: Choosing a Demand Gen Agency for Consistent B2B Growth | OrbitalX | D68: 65 | E68: OrbitalX builds profitable pipeline for lean B2B marketing teams. An entire team, AI system, and performance for the price of one marketing hire. | F68: 4063 | G68: 4 | H68: 2 | I68: 59 | J68: 0 | K68: 248 | L68: 16.73 | M68: Generic meta
A69: https://orbitalx.com/resources/demand-gen-funnel | B69: Article | C69: The Demand Gen Funnel: How to Measure Whether Demand Becomes Pipeline | OrbitalX | D69: 80 | E69: OrbitalX builds profitable pipeline for lean B2B marketing teams. An entire team, AI system, and performance for the price of one marketing hire. | F69: 5448 | G69: 7 | J69: 3 | K69: 363 | L69: 16.09 | M69: Generic meta
A70: https://orbitalx.com/resources/demand-gen-software | B70: Article | C70: Demand Gen Software: How to Choose the Right Stack for Better Pipeline Generation | OrbitalX | D70: 92 | E70: OrbitalX builds profitable pipeline for lean B2B marketing teams. An entire team, AI system, and performance for the price of one marketing hire. | F70: 4095 | G70: 4 | H70: 3 | I70: 17 | J70: 1 | K70: 569 | L70: 17.15 | M70: Generic meta
A71: https://orbitalx.com/resources/demand-gen-strategy | B71: Article | C71: Building An Agile Demand Generation Strategy: The Social Chameleon of The Buyers Journey | OrbitalX | D71: 99 | E71: OrbitalX builds profitable pipeline for lean B2B marketing teams. An entire team, AI system, and performance for the price of one marketing hire. | F71: 5148 | G71: 8 | J71: 0 | K71: 87 | L71: 8.79 | M71: Generic meta
A72: https://orbitalx.com/resources/demand-gen-vs-performance-max | B72: Article | C72: Demand Gen vs. Performance Max: The Google Ads Difference and the Bigger B2B Issue | OrbitalX | D72: 93 | E72: OrbitalX builds profitable pipeline for lean B2B marketing teams. An entire team, AI system, and performance for the price of one marketing hire. | F72: 3301 | G72: 4 | H72: 4 | I72: 20 | J72: 18 | K72: 3004 | L72: 7.78 | M72: Generic meta
A73: https://orbitalx.com/resources/demand-generation-programs | B73: Article | C73: Demand Generation Programs: How to Build a B2B Program That Creates Pipeline | OrbitalX | D73: 87 | E73: OrbitalX builds profitable pipeline for lean B2B marketing teams. An entire team, AI system, and performance for the price of one marketing hire. | F73: 4499 | G73: 6 | H73: 1 | I73: 38 | J73: 0 | K73: 660 | L73: 25.07 | M73: Generic meta
A74: https://orbitalx.com/resources/demandwebs-your-simple-path-to-b2b-growth | B74: Article | C74: DemandWEBS™: Your Simple Path to B2B Growth | OrbitalX | D74: 54 | E74: DemandWebs is a framework for scalable B2B growth. Learn how structured demand generation drives predictable pipeline and revenue. | F74: 664 | G74: 7 | J74: 2 | K74: 11 | L74: 10.91
A75: https://orbitalx.com/resources/do-more-with-less | B75: Article | C75: Do More With Less — B2B Podcast & Video Playlist | OrbitalX | D75: 59 | E75: Do More With Less brings together B2B leaders on lean teams who still expect outsized pipeline results. Watch or listen for practical ideas on efficiency, focus, and measurement. | F75: 511 | G75: 1 | M75: Thin; ≤1 inlink
A76: https://orbitalx.com/resources/do-more-with-less-12-lessons-from-12-months-1 | B76: Article | C76: Do More With Less: 12 lessons from 12 months | OrbitalX | D76: 55 | E76: OrbitalX builds profitable pipeline for lean B2B marketing teams. An entire team, AI system, and performance for the price of one marketing hire. | F76: 2101 | G76: 3 | J76: 0 | K76: 32 | L76: 9.41 | M76: Generic meta
A77: https://orbitalx.com/resources/early-stage-critical-moments-full-episodes | B77: Article | C77: Early Stage Critical Moments Full Episodes | OrbitalX | D77: 53 | E77: OrbitalX builds profitable pipeline for lean B2B marketing teams. An entire team, AI system, and performance for the price of one marketing hire. | F77: 252 | G77: 1 | M77: Generic meta; Thin; ≤1 inlink
A78: https://orbitalx.com/resources/early-stage-critical-moments-podcast | B78: Article | C78: Early Stage Critical Moments Podcast | OrbitalX | D78: 47 | E78: OrbitalX builds profitable pipeline for lean B2B marketing teams. An entire team, AI system, and performance for the price of one marketing hire. | F78: 269 | G78: 1 | J78: 1 | K78: 3 | L78: 2.67 | M78: Generic meta; Thin; ≤1 inlink
A79: https://orbitalx.com/resources/enterprise-account-based-marketing | B79: Article | C79: Enterprise ABM Best Practices for Continuous Optimization | OrbitalX | D79: 68 | E79: OrbitalX builds profitable pipeline for lean B2B marketing teams. An entire team, AI system, and performance for the price of one marketing hire. | F79: 4607 | G79: 7 | H79: 1 | I79: 52 | J79: 0 | K79: 86 | L79: 8.77 | M79: Generic meta
A80: https://orbitalx.com/resources/forget-7-touchpoints-b2b-buyers-now-take-80-interactions-to-convert | B80: Article | C80: Forget 7 Touchpoints. B2B Buyers Now Take 80+ Interactions to Convert. | OrbitalX | D80: 81 | E80: OrbitalX builds profitable pipeline for lean B2B marketing teams. An entire team, AI system, and performance for the price of one marketing hire. | F80: 1420 | G80: 4 | J80: 1 | K80: 45 | L80: 19.04 | M80: Generic meta
A81: https://orbitalx.com/resources/founder-diaries-orbitalx-in-the-philippines | B81: Article | C81: Founder diaries: OrbitalX in the Philippines! | OrbitalX | D81: 56 | E81: OrbitalX builds profitable pipeline for lean B2B marketing teams. An entire team, AI system, and performance for the price of one marketing hire. | F81: 273 | G81: 1 | J81: 0 | K81: 8 | L81: 4.75 | M81: Generic meta; Thin; ≤1 inlink
A82: https://orbitalx.com/resources/from-blocked-to-booked-levantas-journey-with-orbitalx-to-8x-more-meetings | B82: Article | C82: From Blocked to Booked: Levanta's Journey with OrbitalX to 8x More Meetings | OrbitalX | D82: 86 | E82: See how Levanta increased booked meetings by 8x with OrbitalX. Explore the strategy, signals, and outbound systems that unlocked scalable pipeline growth. | F82: 1012 | G82: 10 | J82: 0 | K82: 101 | L82: 9.46
A83: https://orbitalx.com/resources/from-data-overload-to-deal-velocity-how-stackone-scaled-outbound-with-orbitalx | B83: Article | C83: From Data Overload to Deal Velocity: How StackOne scaled outbound with OrbitalX | OrbitalX | D83: 90 | E83: Discover how StackOne transformed data overload into faster deal velocity. Learn how OrbitalX helped scale outbound and unlock consistent pipeline growth. | F83: 600 | G83: 17 | J83: 0 | K83: 1010 | L83: 8.63
A84: https://orbitalx.com/resources/from-data-to-demand-the-strategy-behind-demandwebs | B84: Article | C84: From Data to Demand: The strategy behind DemandWEBS™ | OrbitalX | D84: 63 | E84: Discover the strategy behind DemandWebs and how data drives demand generation. Learn how structured GTM systems create consistent pipeline growth. | F84: 604 | G84: 14 | J84: 3 | K84: 10 | L84: 5.6
A85: https://orbitalx.com/resources/go-to-market-memo-by-stuart-our-co-founder-stuart-dale-breaks-down-winning-gtm-strategies-and-insights-you-can-apply-today | B85: Article | C85: Go-to-Market Memo by Stuart | OrbitalX | D85: 38 | E85: OrbitalX builds profitable pipeline for lean B2B marketing teams. An entire team, AI system, and performance for the price of one marketing hire. | F85: 265 | G85: 1 | J85: 0 | K85: 3 | L85: 7.33 | M85: Generic meta; Thin; ≤1 inlink
A86: https://orbitalx.com/resources/gtm-systems | B86: Article | C86: GTM Systems: The Operating Model Behind Revenue Motion | OrbitalX | D86: 65 | E86: OrbitalX builds profitable pipeline for lean B2B marketing teams. An entire team, AI system, and performance for the price of one marketing hire. | F86: 3547 | G86: 6 | J86: 2 | K86: 344 | L86: 7.22 | M86: Generic meta
A87: https://orbitalx.com/resources/how-a-legal-pioneer-flipped-a-switch-to-start-generating-high-value-conversations-and-leads | B87: Article | C87: How a legal pioneer flipped a switch to start generating high-value conversations and leads | OrbitalX | D87: 102 | E87: OrbitalX builds profitable pipeline for lean B2B marketing teams. An entire team, AI system, and performance for the price of one marketing hire. | F87: 932 | G87: 8 | J87: 0 | K87: 10 | L87: 8.7 | M87: Generic meta
A88: https://orbitalx.com/resources/how-bold-commerce-maximised-growth-in-their-most-critical-channels | B88: Article | C88: How Bold Commerce Maximised Growth in Their Most Critical Channels | OrbitalX | D88: 77 | E88: Learn how Bold Commerce accelerated growth across its most important acquisition channels. Discover the demand generation strategies that improved performance and pipeline. | F88: 603 | G88: 9 | J88: 0 | K88: 133 | L88: 9.5
A89: https://orbitalx.com/resources/how-broken-internal-trust-is-killing-your-bdr-performance | B89: Article | C89: How broken internal trust is killing your BDR performance | OrbitalX | D89: 68 | E89: Internal trust issues can destroy BDR performance. Discover how alignment between teams improves outreach results and pipeline growth. | F89: 987 | G89: 3 | J89: 0 | K89: 20 | L89: 6.95
A90: https://orbitalx.com/resources/how-elastic-is-your-brand-story | B90: Article | C90: How elastic is your brand story? | OrbitalX | D90: 43 | E90: How flexible is your brand story in different markets? Learn how adaptive messaging helps B2B brands stay relevant and influential. | F90: 1123 | G90: 2 | J90: 0 | K90: 9 | L90: 8.89
A91: https://orbitalx.com/resources/how-engagetech-continues-to-build-pipeline-win-deals-and-lead-its-category-with-zero-internal-marketers | B91: Article | C91: How EngageTech drove net-new pipeline and closed-won revenue with OrbitalX | OrbitalX | D91: 85 | E91: Learn how EngageTech built pipeline and closed deals without internal marketers. A case study on category leadership through strategic demand generation. | F91: 573 | G91: 12 | J91: 1 | K91: 120 | L91: 9 | M91: Thin
A92: https://orbitalx.com/resources/how-lean-marketing-teams-can-still-dominate-their-market | B92: Article | C92: Big Uncommon Thinking: How Lean Marketing Teams Can Still Dominate Their Market | OrbitalX | D92: 90 | E92: OrbitalX builds profitable pipeline for lean B2B marketing teams. An entire team, AI system, and performance for the price of one marketing hire. | F92: 466 | G92: 1 | J92: 0 | K92: 59 | L92: 11.47 | M92: Generic meta; Thin; ≤1 inlink
A93: https://orbitalx.com/resources/how-not-to-get-fired-as-a-cmo | B93: Article | C93: How NOT to Get Fired as a CMO | OrbitalX | D93: 40 | E93: Practical advice for CMOs navigating modern growth challenges. Learn how to align marketing with revenue and prove measurable impact. | F93: 886 | G93: 3 | J93: 0 | K93: 3 | L93: 8.33
A94: https://orbitalx.com/resources/how-occy-unlocked-faster-growth-without-more-headcount | B94: Article | C94: How occy unlocked faster growth without more headcount | OrbitalX | D94: 65 | E94: Explore how Occy accelerated growth without expanding its team. This case study shows how smarter GTM execution drives scalable revenue results. | F94: 547 | G94: 10 | J94: 1 | K94: 142 | L94: 6.98 | M94: Thin
A95: https://orbitalx.com/resources/how-the-smartest-hire-grew-pipeline-at-private-equity-backed-cylindo-without-a-marketing-team | B95: Article | C95: How Cylindo rapidly generated predictable pipeline with OrbitalX | OrbitalX | D95: 75 | E95: Discover how Cylindo grew its pipeline without a traditional marketing team. Learn the GTM strategies that helped a PE-backed company generate consistent demand. | F95: 926 | G95: 13 | H95: 1 | I95: 86 | J95: 2 | K95: 246 | L95: 9.86
A96: https://orbitalx.com/resources/how-to-improve-webinar-marketing-6-reasons-6-solutions | B96: Article | C96: How to Improve Webinar Marketing: 6 Reasons, 6 Solutions | OrbitalX | D96: 67 | E96: Struggling with webinar performance? Discover six reasons webinars fail and practical solutions to improve attendance and engagement. | F96: 1037 | G96: 12 | J96: 1 | K96: 14 | L96: 9.14
A97: https://orbitalx.com/resources/how-to-measure-account-based-marketing | B97: Article | C97: How to Measure Account Based Marketing: The Metrics That Drive Growth | OrbitalX | D97: 80 | E97: OrbitalX builds profitable pipeline for lean B2B marketing teams. An entire team, AI system, and performance for the price of one marketing hire. | F97: 2766 | G97: 4 | J97: 0 | K97: 185 | L97: 12.19 | M97: Generic meta
A98: https://orbitalx.com/resources/how-to-measure-marketing-qualified-leads-effectively | B98: Article | C98: How to Measure Marketing Qualified Leads Effectively | OrbitalX | D98: 63 | E98: Learn how to measure marketing qualified leads accurately. Discover frameworks and metrics that align marketing with revenue results. | F98: 847 | G98: 8 | J98: 1 | K98: 1700 | L98: 6.95
A99: https://orbitalx.com/resources/how-to-prevent-a-pipeline-performance-slump-in-2025-without-increasing-spend | B99: Article | C99: How to Prevent a Pipeline Performance Slump in 2025 Without Increasing Spend | OrbitalX | D99: 87 | E99: OrbitalX builds profitable pipeline for lean B2B marketing teams. An entire team, AI system, and performance for the price of one marketing hire. | F99: 273 | G99: 1 | J99: 0 | K99: 1 | L99: 3 | M99: Generic meta; Thin; ≤1 inlink
A100: https://orbitalx.com/resources/how-to-prevent-a-pipeline-performance-slump-without-increasing-spend | B100: Article | C100: How to prevent a pipeline performance slump without increasing spend | OrbitalX | D100: 79 | E100: OrbitalX builds profitable pipeline for lean B2B marketing teams. An entire team, AI system, and performance for the price of one marketing hire. | F100: 267 | G100: 1 | J100: 0 | K100: 1 | L100: 10 | M100: Generic meta; Thin; ≤1 inlink
A101: https://orbitalx.com/resources/how-to-unlock-your-full-target-market-with-effective-demand-generation | B101: Article | C101: How to Unlock Your Full Target Market with Effective Demand Generation | OrbitalX | D101: 81 | E101: OrbitalX builds profitable pipeline for lean B2B marketing teams. An entire team, AI system, and performance for the price of one marketing hire. | F101: 274 | G101: 1 | M101: Generic meta; Thin; ≤1 inlink
A102: https://orbitalx.com/resources/inbound-lead-generation | B102: Article | C102: Inbound Lead Generation: How It Evolved as B2B Buyers Changed | OrbitalX | D102: 72 | E102: OrbitalX builds profitable pipeline for lean B2B marketing teams. An entire team, AI system, and performance for the price of one marketing hire. | F102: 4447 | G102: 4 | J102: 0 | K102: 62 | L102: 6.9 | M102: Generic meta
...

Sheet Semrush Keywords
A1: Semrush organic positions (US, 12 Oct 2026)
A2: Raw export, de-duplicated (one exact duplicate row removed).
A4: Keyword | B4: Position | C4: Volume | D4: KD | E4: CPC ($) | F4: URL | G4: Traffic | H4: Intent | I4: SERP features
A5: abm personalization tools | B5: 46 | C5: 70 | D5: 25 | E5: 0 | F5: https://orbitalx.com/resources/account-based-marketing-personalization | G5: 0 | H5: informational | I5: Video, People also ask, Related searches, AI overview
A6: abm personalization tools | B6: 52 | C6: 70 | D6: 25 | E6: 0 | F6: https://orbitalx.com/resources/account-based-marketing-tools | G6: 0 | H6: informational | I6: Video, People also ask, Related searches, AI overview
A7: abm personalization tools | B7: 78 | C7: 70 | D7: 25 | E7: 0 | F7: https://orbitalx.com/resources/account-based-marketing-personalization | G7: 0 | H7: informational | I7: Video, People also ask, Related searches, AI overview
A8: abm tools with contact-level intent | B8: 57 | C8: 70 | D8: 14 | E8: 0 | F8: https://orbitalx.com/resources/account-based-marketing-tools | G8: 0 | H8: informational | I8: Reviews, Video, Ads bottom, People also ask, Related searches, AI overview
A9: abx campaign | B9: 80 | C9: 110 | D9: 13 | E9: 46.3 | F9: https://orbitalx.com/services/abm | G9: 0 | H9: informational | I9: Sitelinks, Reviews, Video, Video Carousel, People also ask, Related searches, AI overview
A10: abx platforms | B10: 80 | C10: 50 | D10: 12 | E10: 34.47 | F10: https://orbitalx.com/resources/account-based-marketing-software | G10: 0 | H10: informational | I10: Video, People also ask, Related searches, AI overview
A11: account based advertising software market | B11: 34 | C11: 70 | D11: 32 | E11: 0 | F11: https://orbitalx.com/resources/account-based-marketing-software | G11: 0 | H11: commercial, informational | I11: Sitelinks, Reviews, Video, Related searches, AI overview
A12: account based everything b2b marketing | B12: 58 | C12: 40 | D12: 35 | E12: 0 | F12: https://orbitalx.com/resources/b2b-account-based-marketing | G12: 0 | H12: informational | I12: Sitelinks, Reviews, Video, Video Carousel, Related searches, AI overview
A13: account based everything b2b marketing | B13: 59 | C13: 40 | D13: 35 | E13: 0 | F13: https://orbitalx.com/resources/b2b-account-based-marketing | G13: 0 | H13: informational | I13: Sitelinks, Reviews, Video, Video Carousel, Related searches, AI overview
A14: account based marketing content strategy | B14: 33 | C14: 140 | D14: 24 | E14: 0 | F14: https://orbitalx.com/resources/b2b-account-based-marketing | G14: 0 | H14: informational | I14: Image pack, Sitelinks, Video, People also ask, AI overview
A15: account based marketing for enterprise | B15: 52 | C15: 40 | D15: 40 | E15: 0 | F15: https://orbitalx.com/resources/enterprise-account-based-marketing | G15: 0 | H15: informational | I15: Sitelinks, Video, People also ask, Related searches, AI overview
A16: account based marketing planning services | B16: 69 | C16: 170 | D16: 35 | E16: 0 | F16: https://orbitalx.com/resources/account-based-marketing-tools | G16: 0 | H16: informational | I16: Sitelinks, Reviews, Video, People also ask, Related searches, AI overview
... A18: account based marketing platform | B18: 73 | C18: 170 | D18: 57 | E18: 91.81 | F18: https://orbitalx.com/resources/account-based-marketing-tools | G18: 0 | H18: commercial, informational | I18: Sitelinks, Reviews, Video, People also ask, Related searches, AI overview
A19: account based marketing platforms with intent signals | B19: 51 | C19: 50 | E19: 0 | F19: https://orbitalx.com/resources/account-based-marketing-tools | G19: 0 | H19: commercial, informational | I19: Sitelinks, Reviews, Video, People also ask, Related searches, AI overview
A20: account based marketing solutions | B20: 79 | C20: 210 | D20: 50 | E20: 0 | F20: https://orbitalx.com/resources/account-based-marketing-tools | G20: 0 | H20: informational | I20: Sitelinks, Reviews, Video, People also ask, Related searches, AI overview
A21: account based marketing vendors | B21: 76 | C21: 320 | D21: 47 | E21: 29.05 | F21: https://orbitalx.com/resources/account-based-marketing-tools | G21: 0 | H21: informational | I21: Sitelinks, Reviews, Video, People also ask, Related searches, AI overview
A22: account based selling strategy software | B22: 31 | C22: 40 | D22: 16 | E22: 0 | F22: https://orbitalx.com/resources/account-based-marketing-software | G22: 0 | H22: informational | I22: Sitelinks, Reviews, Video, Related searches, Discussions and forums, AI overview
A23: account-based marketing solutions | B23: 64 | C23: 40 | D23: 37 | E23: 0 | F23: https://orbitalx.com/resources/account-based-marketing-tools | G23: 0 | H23: commercial, informational | I23: Sitelinks, Video, People also ask, Related searches, AI overview
A24: account-based marketing tool | B24: 63 | C24: 30 | D24: 41 | E24: 60.51 | F24: https://orbitalx.com/resources/account-based-marketing-tools | G24: 0 | H24: commercial, informational | I24: Reviews, Video, People also ask, Related searches, AI overview
A25: account-based outreach software | B25: 41 | C25: 50 | D25: 18 | E25: 0 | F25: https://orbitalx.com/resources/account-based-marketing-tools | G25: 0 | H25: commercial, informational | I25: Reviews, Video, People also ask, Related searches, AI overview
A26: ai marketing agent qualify intent book meetings | B26: 13 | C26: 50 | D26: 1 | E26: 0 | F26: https://orbitalx.com/resources/ai-lead-generation | G26: 0 | H26: informational | I26: Sitelinks, Reviews, Video, People also ask, AI overview
A27: asteroidx | B27: 51 | C27: 110 | D27: 30 | E27: 14.59 | F27: https://orbitalx.com/ | G27: 0 | H27: navigational | I27: Knowledge panel, Image pack, Sitelinks, Reviews, Video, Related searches, AI overview
A28: b2b accounts | B28: 20 | C28: 140 | D28: 20 | E28: 10.91 | F28: https://orbitalx.com/resources/b2b-account-based-marketing | G28: 0 | H28: informational | I28: Image pack, Sitelinks, Reviews, Video, Image, People also ask, Related searches, AI overview
A29: b2b go-to-market optimization partners | B29: 31 | C29: 40 | E29: 0 | F29: https://orbitalx.com/resources/b2b-go-to-market-strategy | G29: 0 | H29: informational | I29: Video, Video Carousel, People also ask, Related searches, AI overview
A30: b2b go-to-market partners for logistics brands | B30: 64 | C30: 40 | D30: 4 | E30: 0 | F30: https://orbitalx.com/resources/b2b-go-to-market-strategy | G30: 0 | H30: informational | I30: Sitelinks, Reviews, Video, People also ask, Related searches, AI overview
A31: b2b software companies disjointed sales marketing systems revenue impact | B31: 33 | C31: 50 | E31: 0 | F31: https://orbitalx.com/resources/lead-generation-chatbot | G31: 0 | H31: informational | I31: Reviews, Video, People also ask, Related searches, AI overview
A32: best account-based marketing platform for demand generation | B32: 49 | C32: 40 | D32: 26 | E32: 0 | F32: https://orbitalx.com/resources/account-based-marketing-tools | G32: 0 | H32: commercial | I32: Sitelinks, Reviews, Video, People also ask, AI overview
A33: billionx | B33: 19 | C33: 110 | D33: 0 | E33: 0 | F33: https://orbitalx.com/ | G33: 0 | H33: informational | I33: Sitelinks, Video
A34: deltay.xyz target audience b2b smes | B34: 28 | C34: 1300 | D34: 12 | E34: 0 | F34: https://orbitalx.com/resources | G34: 1 | H34: informational | I34: Reviews, Video, AI overview
A35: demand gen company | B35: 25 | C35: 480 | D35: 43 | E35: 39.51 | F35: https://orbitalx.com/blog-categories/demand-generation | G35: 0 | H35: informational | I35: Sitelinks, Reviews, Video, People also ask, Related searches, AI overview
A36: demand gen firm | B36: 59 | C36: 110 | D36: 38 | E36: 0 | F36: https://orbitalx.com/resources/demand-gen-agency | G36: 0 | H36: informational | I36: Sitelinks, Video, People also ask, Related searches, AI overview
A37: demand gen firm | B37: 60 | C37: 110 | D37: 38 | E37: 0 | F37: https://orbitalx.com/resources/demand-gen-agency | G37: 0 | H37: informational | I37: Sitelinks, Video, People also ask, Related searches, AI overview
A38: demand gen software | B38: 17 | C38: 140 | D38: 23 | E38: 19.25 | F38: https://orbitalx.com/resources/demand-gen-software | G38: 0 | H38: informational | I38: Sitelinks, Video, Video Carousel, People also ask, Related searches, AI overview
A39: demand gen vs performance max | B39: 20 | C39: 140 | D39: 10 | E39: 34.95 | F39: https://orbitalx.com/resources/demand-gen-vs-performance-max | G39: 0 | H39: commercial | I39: Sitelinks, Reviews, Video, People also ask, Related searches, AI overview
A40: demand gen vs pmax | B40: 28 | C40: 70 | D40: 7 | E40: 0 | F40: https://orbitalx.com/resources/demand-gen-vs-performance-max | G40: 0 | H40: commercial | I40: Sitelinks, Reviews, Video, People also ask, Related searches, AI overview
A41: demand gen vs. lead gen | B41: 38 | C41: 40 | D41: 1 | E41: 4.73 | F41: https://orbitalx.com/resources/demand-gen-vs-performance-max | G41: 0 | H41: commercial | I41: Image pack, Reviews, Video, People also ask, AI overview
A42: demand generation program | B42: 38 | C42: 260 | D42: 34 | E42: 25.16 | F42: https://orbitalx.com/resources/demand-generation-programs | G42: 0 | H42: informational | I42: Sitelinks, Reviews, Video, People also ask, Related searches, AI overview
A43: demand generation recruiters | B43: 61 | C43: 40 | E43: 0 | F43: https://orbitalx.com/resources/demand-gen-agency | G43: 0 | H43: informational | I43: Reviews, Video, Ads top, People also ask, Related searches, AI overview
A44: demandx | B44: 26 | C44: 50 | D44: 12 | E44: 3.26 | F44: https://orbitalx.com/blog-categories/demand-generation | G44: 0 | H44: informational | I44: Image pack, Sitelinks, Reviews, Video, Related searches, AI overview
A45: demandx | B45: 70 | C45: 50 | D45: 12 | E45: 3.26 | F45: https://orbitalx.com/resources/demand-gen-software | G45: 0 | H45: informational | I45: Image pack, Sitelinks, Reviews, Video, Related searches, AI overview
A46: difference between demand gen and lead gen | B46: 69 | C46: 50 | D46: 1 | E46: 18.18 | F46: https://orbitalx.com/resources/lead-generation-vs-demand-generation-understanding-the-differences-and-benefits | G46: 0 | H46: informational | I46: Reviews, Video, People also ask, Related searches, AI overview
A47: difference between demand gen and lead gen | B47: 92 | C47: 50 | D47: 1 | E47: 18.18 | F47: https://orbitalx.com/resources/lead-generation-vs-demand-generation-understanding-the-differences-and-benefits | G47: 0 | H47: informational | I47: Reviews, Video, People also ask, Related searches, AI overview
A48: enterprise abm teams results turtl | B48: 17 | C48: 40 | D48: 0 | E48: 0 | F48: https://orbitalx.com/resources/account-based-marketing-tools | G48: 0 | H48: informational, navigational | I48: Reviews, Video, AI overview
A49: google ads demand gen vs performance max optimization | B49: 47 | C49: 70 | D49: 18 | E49: 0 | F49: https://orbitalx.com/resources/demand-gen-vs-performance-max | G49: 0 | H49: commercial | I49: Sitelinks, Reviews, Video, Video Carousel, People also ask, Related searches, Discussions and forums, AI overview
A50: gtm engineering signal-driven flywheels definition | B50: 64 | C50: 110 | D50: 8 | E50: 0 | F50: https://orbitalx.com/resources/the-4-step-flywheel-effect-a-proven-evergreen-framework-for-gtm-success | G50: 0 | H50: informational | I50: Reviews, Video, People also ask, Related searches, AI overview
A51: how are other marketing teams solving complex rendering performance requirements | B51: 22 | C51: 50 | E51: 0 | F51: https://orbitalx.com/resources/performance-marketing-optimization | G51: 0 | H51: informational | I51: Sitelinks, Reviews, Video, People also ask, Related searches, AI overview
A52: larger market formula | B52: 2 | C52: 40 | D52: 0 | E52: 0 | F52: https://orbitalx.com/resources/the-larger-market-formula-your-next-b2b-software-success-strategy | G52: 1 | H52: informational | I52: Image pack, Reviews, Video, Image, People also ask, Related searches, AI overview
A53: lead scoring model for seo growth intent | B53: 45 | C53: 880 | D53: 24 | E53: 0 | F53: https://orbitalx.com/resources/b2b-marketing | G53: 0 | H53: informational | I53: Video, People also ask, AI overview
A54: leading account-based marketing consulting options for large software firms | B54: 85 | C54: 40 | D54: 11 | E54: 0 | F54: https://orbitalx.com/resources/account-based-marketing-tools | G54: 0 | H54: commercial, informational | I54: Reviews, Video, Related searches, AI overview
A55: nexxi b2b go-to-market enablement ai-native teams | B55: 33 | C55: 50 | D55: 13 | E55: 0 | F55: https://orbitalx.com/resources/b2b-go-to-market-strategy | G55: 0 | H55: informational | I55: Reviews, Video, AI overview
A56: nexxi b2b go-to-market enablement alternatives | B56: 34 | C56: 70 | D56: 9 | E56: 0 | F56: https://orbitalx.com/resources/b2b-go-to-market-strategy | G56: 0 | H56: commercial | I56: Reviews, Video, People also ask, Related searches, AI overview
A57: orbit x | B57: 51 | C57: 90 | D57: 19 | E57: 2.39 | F57: https://app.orbitalx.com/ | G57: 0 | H57: informational | I57: Sitelinks, Reviews, Video, People also ask, Related searches, AI overview
A58: orbit-x | B58: 46 | C58: 50 | D58: 24 | E58: 2.39 | F58: https://app.orbitalx.com/ | G58: 0 | H58: informational | I58: Sitelinks, Reviews, Video, People also ask, Popular products, Related searches, AI overview
A59: orbital company | B59: 70 | C59: 170 | D59: 60 | E59: 4.72 | F59: https://orbitalx.com/ | G59: 0 | H59: informational | I59: Local pack, Sitelinks, Video, People also ask, Related searches, AI overview
A60: orbital inc. | B60: 68 | C60: 110 | D60: 51 | E60: 0 | F60: https://orbitalx.com/ | G60: 0 | H60: navigational | I60: Sitelinks, Video, People also ask, Related searches, AI overview
A61: orbital llc | B61: 55 | C61: 50 | D61: 33 | E61: 0 | F61: https://orbitalx.com/ | G61: 0 | H61: informational | I61: Video, Related searches, AI overview
A62: orbital management | B62: 47 | C62: 40 | D62: 0 | E62: 1.96 | F62: https://orbitalx.com/ | G62: 0 | H62: informational | I62: Video, People also ask, Related searches, AI overview
A63: orbital software | B63: 75 | C63: 90 | D63: 46 | E63: 9.58 | F63: https://orbitalx.com/ | G63: 0 | H63: informational | I63: Sitelinks, Reviews, Video, People also ask, Related searches, AI overview
... A89: programmatic advertising b2b | B89: 1 | C89: 90 | D89: 18 | E89: 43.1 | F89: https://orbitalx.com/resources/b2b-account-based-marketing | G89: 0 | H89: informational | I89: Sitelinks, Reviews, Video, People also ask, AI overview
A90: top abm software providers | B90: 47 | C90: 40 | E90: 0 | F90: https://orbitalx.com/resources/account-based-marketing-tools | G90: 0 | H90: commercial | I90: Sitelinks, Reviews, Video, Ads bottom, People also ask, Related searches, AI overview
A91: top abm software providers | B91: 50 | C91: 40 | E91: 0 | F91: https://orbitalx.com/resources/account-based-marketing-tools | G91: 0 | H91: commercial | I91: Sitelinks, Reviews, Video, Ads bottom, People also ask, Related searches, AI overview
A92: top abm tools programmatic account-based advertising | B92: 52 | C92: 40 | D92: 33 | E92: 0 | F92: https://orbitalx.com/resources/account-based-marketing-tools | G92: 0 | H92: commercial | I92: Sitelinks, Video, People also ask, Related searches, AI overview
A93: top abm tools programmatic account-based advertising | B93: 69 | C93: 40 | D93: 33 | E93: 0 | F93: https://orbitalx.com/resources/account-based-marketing-tools | G93: 0 | H93: commercial | I93: Sitelinks, Video, People also ask, Related searches, AI overview
A94: top services for scaling account-based marketing | B94: 39 | C94: 50 | E94: 0 | F94: https://orbitalx.com/resources/account-based-marketing-tools | G94: 0 | H94: commercial, informational | I94: Sitelinks, Video, People also ask, Related searches, AI overview
A95: withorbital | B95: 14 | C95: 30 | D95: 27 | E95: 31.71 | F95: https://orbitalx.com/resources | G95: 0 | H95: navigational | I95: Sitelinks, Video, Related searches
A96: withorbital | B96: 19 | C96: 30 | D96: 27 | E96: 31.71 | F96: https://orbitalx.com/ | G96: 0 | H96: navigational | I96: Sitelinks, Video, Related searches
A97: x orbital | B97: 3 | C97: 50 | D97: 36 | E97: 0 | F97: https://orbitalx.com/ | G97: 0 | H97: informational, navigational | I97: Image pack, Sitelinks, Reviews, Video, Related searches
A98: x orbital | B98: 18 | C98: 50 | D98: 36 | E98: 0 | F98: https://orbitalx.com/team | G98: 0 | H98: informational, navigational | I98: Image pack, Sitelinks, Reviews, Video, Related searches
A99: yieldify | B99: 20 | C99: 110 | D99: 17 | E99: 25.95 | F99: https://orbitalx.com/resources/behind-the-numbers-how-yieldify-made-every-rep-count | G99: 0 | H99: informational | I99: Sitelinks, Reviews, Related searches, AI overview
A100: yieldify | B100: 21 | C100: 110 | D100: 17 | E100: 25.95 | F100: https://orbitalx.com/resources/behind-the-numbers-how-yieldify-made-every-rep-count | G100: 0 | H100: informational | I100: Sitelinks, Reviews, Related searches, AI overview

Sheet GSC Daily
A1: Google Search Console: daily performance
A2: Source: GSC export, Web search, last 3 months (11 Jul – 10 Oct 2026). Month column is a formula.
A4: Date | B4: Clicks | C4: Impressions | D4: CTR | E4: Avg position | F4: Month
A5: 46214 | B5: 0 | C5: 183 | D5: =IFERROR(B5/C5,0) -> 0 | E5: 24.2 | F5: =TEXT(A5,"yyyy-mm") -> 2026-07
A6: 46215 | B6: 2 | C6: 238 | D6: =IFERROR(B6/C6,0) -> 0.0084033613 | E6: 20 | F6: =TEXT(A6,"yyyy-mm") -> 2026-07
A7: 46216 | B7: 9 | C7: 239 | D7: =IFERROR(B7/C7,0) -> 0.037656904 | E7: 20.5 | F7: =TEXT(A7,"yyyy-mm") -> 2026-07
A8: 46217 | B8: 14 | C8: 279 | D8: =IFERROR(B8/C8,0) -> 0.050179211 | E8: 15.3 | F8: =TEXT(A8,"yyyy-mm") -> 2026-07
A9: 46218 | B9: 5 | C9: 274 | D9: =IFERROR(B9/C9,0) -> 0.018248175 | E9: 23.3 | F9: =TEXT(A9,"yyyy-mm") -> 2026-07
A10: 46219 | B10: 11 | C10: 303 | D10: =IFERROR(B10/C10,0) -> 0.03630363 | E10: 24.1 | F10: =TEXT(A10,"yyyy-mm") -> 2026-07
A11: 46220 | B11: 2 | C11: 239 | D11: =IFERROR(B11/C11,0) -> 0.0083682008 | E11: 25 | F11: =TEXT(A11,"yyyy-mm") -> 2026-07
A12: 46221 | B12: 0 | C12: 199 | D12: =IFERROR(B12/C12,0) -> 0 | E12: 22.1 | F12: =TEXT(A12,"yyyy-mm") -> 2026-07
A13: 46222 | B13: 1 | C13: 231 | D13: =IFERROR(B13/C13,0) -> 0.0043290043 | E13: 20.8 | F13: =TEXT(A13,"yyyy-mm") -> 2026-07
A14: 46223 | B14: 10 | C14: 298 | D14: =IFERROR(B14/C14,0) -> 0.033557047 | E14: 21.5 | F14: =TEXT(A14,"yyyy-mm") -> 2026-07
A15: 46224 | B15: 12 | C15: 269 | D15: =IFERROR(B15/C15,0) -> 0.044609665 | E15: 19.1 | F15: =TEXT(A15,"yyyy-mm") -> 2026-07
A16: 46225 | B16: 13 | C16: 319 | D16: =IFERROR(B16/C16,0) -> 0.040752351 | E16: 20.4 | F16: =TEXT(A16,"yyyy-mm") -> 2026-07
... A96: 46305 | B96: 2 | C96: 141 | D96: =IFERROR(B96/C96,0) -> 0.014184397 | E96: 14.5 | F96: =TEXT(A96,"yyyy-mm") -> 2026-10

Sheet GSC Countries
A1: Google Search Console: countries
A2: Source: GSC export, last 3 months. CTR recomputed as a formula.
A4: Country | B4: Clicks | C4: Impressions | D4: CTR | E4: Avg position
A5: United Kingdom | B5: 334 | C5: 3419 | D5: =IFERROR(B5/C5,0) -> 0.097689383 | E5: 12.52
A6: Philippines | B6: 142 | C6: 1462 | D6: =IFERROR(B6/C6,0) -> 0.097127223 | E6: 9.82
A7: United States | B7: 114 | C7: 15035 | D7: =IFERROR(B7/C7,0) -> 0.0075823079 | E7: 20.04
A8: South Africa | B8: 46 | C8: 162 | D8: =IFERROR(B8/C8,0) -> 0.28395062 | E8: 4.1
A9: India | B9: 24 | C9: 1235 | D9: =IFERROR(B9/C9,0) -> 0.019433198 | E9: 13.34
A10: Sweden | B10: 22 | C10: 128 | D10: =IFERROR(B10/C10,0) -> 0.171875 | E10: 13.05
A11: Netherlands | B11: 16 | C11: 984 | D11: =IFERROR(B11/C11,0) -> 0.016260163 | E11: 26.59
A12: Germany | B12: 14 | C12: 1190 | D12: =IFERROR(B12/C12,0) -> 0.011764706 | E12: 14.86
A13: Spain | B13: 13 | C13: 270 | D13: =IFERROR(B13/C13,0) -> 0.048148148 | E13: 16.14
A14: Canada | B14: 11 | C14: 489 | D14: =IFERROR(B14/C14,0) -> 0.022494888 | E14: 8.33
A15: France | B15: 9 | C15: 250 | D15: =IFERROR(B15/C15,0) -> 0.036 | E15: 15.44
A16: Thailand | B16: 9 | C16: 192 | D16: =IFERROR(B16/C16,0) -> 0.046875 | E16: 16.01
... A163: Mozambique | B163: 0 | C163: 1 | D163: =IFERROR(B163/C163,0) -> 0 | E163: 41

Sheet Sources & Method
A1: Sources and method
A4: Item | B4: Detail
A5: Site crawl | B5: All 152 sitemap URLs fetched 13 Oct 2026: status, title, meta, canonical, robots, OG, headings, JSON-LD, images, links, word count; plus robots.txt, URL variants, pagination, 404, app. subdomain.
A6: Semrush | B6: Organic Positions + Organic Pages, US database, 12 Oct 2026. Traffic figures are estimates. No UK export yet.
A7: Google Search Console | B7: Web search, last 3 months (11 Jul – 10 Oct 2026): daily chart, countries, devices, pages. No Queries export was provided.
A8: SERP research | B8: Live web searches on 13 Oct 2026 for agency, ABM, demand gen and GTM terms. Competitor pricing and clients come from third-party roundups/directories and are indicative only.
A9: Assumptions | B9: Target CTR by position (Page Opportunities, blue cells) is a conservative assumption, not a measured benchmark.
A10: Not verified | B10: Backlinks, Core Web Vitals, index coverage report, UK rankings, HTTP→HTTPS redirect, subdomain microsites (SSL handshake failed from the audit environment), Webflow-hosted logo.
A11: Source URLs | B11: clutch.co/profile/orbitalx · g2.com/sellers/strategicabm · gripped.io/digital-marketing-strategy/b2b-abm-agency/ · directiveconsulting.com/uk/blog/demand-generation-agencies/ · poweredbysearch.com/learn/best-b2b-demand-generation-agencies/ · blendb2b.com/resources/best-b2b-demand-generation-agencies-uk-2026 · polarisagency.com/marketing-insights/best-demand-gen-agencies-b2b-uk/ · b2bmarketing.net/top-uk-demand-generation-agencies-2026-blog/ · digitallitmus.com/blog/best-abm-agencies · onemetrik.com/blogs/best-abm-agencies/ · gtm8020.com/blog/best-abm-agencies-b2b-saas · revvgrowth.com/abm/abm-digital-marketing-agency · thegrowthsyndicate.com/agencies/top-account-based-marketing-agencies-uk · bestabmagencies.com · piperocket.digital/list/best-abm-agencies/ · 310creative.com/blog/top-abm-agencies/ · o8.agency/services/account-based-marketing-agency · teamlewis.com · searchatlas.com/blog/demand-gen-vs-performance-max/ · seerinteractive.com/insights/google-performance-max-vs-demand-gen · abmatic.ai/blog/best-account-based-marketing-tools-2026 · userled.io/articles/best-abm-tools-2026 · nektar.ai · salesforge.ai/directory/agencies/strategicabm · syncgtm.com/directory
